{"skeleton":{"hash":"NoX+JuwsRXLOlpN8ej8u2qg7Y5I","spine":"3.7.94","width":190,"height":331.07,"images":"./images/","audio":""},"bones":[{"name":"root"},{"name":"bone","parent":"root","length":18,"x":-3.55,"y":69.53,"color":"03a376ff"},{"name":"bone2","parent":"bone","length":19.71,"rotation":-96.38,"x":-2.92,"y":-3.15},{"name":"bone3","parent":"bone2","length":10.33,"rotation":3.35,"x":19.71},{"name":"bone4","parent":"bone3","length":16.35,"rotation":-2.58,"x":10.33},{"name":"bone5","parent":"bone","length":14.25,"rotation":-54.78,"x":10.14,"y":0.14},{"name":"bone6","parent":"bone5","length":12.62,"rotation":13.3,"x":16.04,"y":-0.09},{"name":"bone7","parent":"bone6","length":17.63,"rotation":2.47,"x":12.62},{"name":"bone8","parent":"bone","length":15.93,"rotation":-117.67,"x":-10.69,"y":-0.68},{"name":"bone9","parent":"bone8","length":20.35,"rotation":-3.56,"x":15.93},{"name":"bone10","parent":"bone","length":9.04,"rotation":89.13,"x":-1.37,"y":5.48},{"name":"bone11","parent":"bone10","length":7.67,"rotation":0.87,"x":9.04},{"name":"bone12","parent":"bone11","length":9.24,"rotation":-6.81,"x":7.67},{"name":"bone13","parent":"bone12","length":12.62,"rotation":9.3,"x":9.24},{"name":"bone16","parent":"bone12","length":13.05,"rotation":-74.06,"x":5.07,"y":-2.23},{"name":"bone17","parent":"bone16","length":19.91,"rotation":-23.17,"x":13.05},{"name":"bone18","parent":"bone17","length":13.42,"rotation":-32.01,"x":19.91},{"name":"bone19","parent":"bone18","length":6.19,"rotation":4.05,"x":13.42},{"name":"bone20","parent":"bone12","length":6.3,"rotation":82.19,"x":3.89,"y":0.61},{"name":"bone21","parent":"bone16","x":9.75,"y":2.93},{"name":"bone22","parent":"bone16","x":10.02,"y":-6.87},{"name":"bone14","parent":"bone11","x":2.06,"y":-8.18},{"name":"bone15","parent":"bone10","x":5.75,"y":-12.83},{"name":"bone23","parent":"bone10","x":6.36,"y":5.07},{"name":"bone24","parent":"bone11","x":2.65,"y":4.59},{"name":"bone25","parent":"bone20","x":5.47,"y":-1.61},{"name":"bone26","parent":"bone25","x":0.55,"y":4.82},{"name":"bone28","parent":"bone17","x":9.29,"y":-6.35},{"name":"bone29","parent":"bone16","length":14.82,"rotation":-41.43,"x":13.44,"y":0.31},{"name":"bone30","parent":"bone29","length":7.96,"rotation":-16.37,"x":14.82},{"name":"bone31","parent":"bone30","length":5.26,"rotation":138.67,"x":7.96},{"name":"bone32","parent":"bone31","length":4.11,"rotation":94.01,"x":-0.72,"y":1.58},{"name":"bone33","parent":"bone32","length":5.76,"rotation":-6.16,"x":4.11},{"name":"bone34","parent":"bone","length":32.27,"rotation":-59.17,"x":6.67,"y":-8.6},{"name":"bone35","parent":"bone34","length":38.46,"rotation":-18.3,"x":32.27},{"name":"bone36","parent":"bone35","length":11.7,"rotation":18.94,"x":38.46},{"name":"bone37","parent":"bone","length":31.14,"rotation":-114.6,"x":-9.57,"y":-8.3},{"name":"bone38","parent":"bone37","length":28.48,"rotation":37.91,"x":31.14},{"name":"bone39","parent":"bone38","length":7.47,"rotation":-74.7,"x":28.48},{"name":"bone40","parent":"bone39","length":8.72,"rotation":-20.76,"x":7.47},{"name":"bone41","parent":"bone","length":18.03,"rotation":-89.05,"x":0.71,"y":-22.46},{"name":"bone42","parent":"bone","length":13.56,"rotation":-67.38,"x":9.65,"y":-26.93},{"name":"bone43","parent":"bone20","length":16.98,"rotation":97.06,"x":4.92,"y":2.38},{"name":"bone44","parent":"bone43","length":15.67,"rotation":-24.62,"x":16.98},{"name":"bone45","parent":"bone44","length":6.28,"rotation":9.87,"x":15.67},{"name":"bone46","parent":"bone45","x":-10.56,"y":8.07},{"name":"bone47","parent":"bone10","x":1.83,"y":-8.7,"color":"31ff00ff"},{"name":"bone48","parent":"bone11","x":1.35,"y":-14.89,"color":"32ff00ff"},{"name":"bone49","parent":"bone12","x":5.45,"y":-13.96,"color":"31ff00ff"},{"name":"bone50","parent":"bone12","x":1.8,"y":3.87,"color":"31ff00ff"},{"name":"bone51","parent":"bone11","x":1.48,"y":3.88,"color":"31ff00ff"},{"name":"bone52","parent":"bone10","x":0.87,"y":5.02,"color":"31ff00ff"},{"name":"bone53","parent":"bone20","length":19.58,"rotation":101.81,"x":4.71,"y":10.21,"color":"ff2000ff"},{"name":"bone54","parent":"bone53","length":15.02,"rotation":-5,"x":19.83,"y":-0.11,"color":"ff2000ff"},{"name":"bone55","parent":"bone54","length":6.14,"rotation":3.32,"x":15.02,"color":"ff2000ff"},{"name":"bone57","parent":"bone55","length":8.41,"rotation":-3.99,"x":12.77,"y":-2.19},{"name":"bone56","parent":"bone","length":7.7,"rotation":-99.23,"x":-0.3,"y":-5.01,"color":"03a376ff"},{"name":"bone58","parent":"bone56","length":10.03,"rotation":3.25,"x":7.7,"color":"03a376ff"},{"name":"bone59","parent":"bone58","length":6.67,"rotation":1.89,"x":10.03,"color":"03a376ff"},{"name":"bone60","parent":"bone59","length":6.68,"rotation":-1.62,"x":6.67,"color":"03a376ff"},{"name":"bone61","parent":"bone60","length":6.84,"rotation":5.71,"x":6.68,"color":"03a376ff"},{"name":"bone62","parent":"bone61","length":6.86,"rotation":-4.76,"x":6.84,"color":"03a376ff"},{"name":"bone63","parent":"root","length":17.89,"rotation":-75.03,"x":-23.4,"y":-2.17,"color":"03a376ff"},{"name":"bone64","parent":"root","length":20.94,"rotation":-52.8,"x":32.48,"y":-18.25,"color":"03a376ff"},{"name":"bone65","parent":"root","length":16.02,"rotation":-72.47,"x":3.34,"y":-9.4,"color":"03a376ff"},{"name":"bone66","parent":"bone45","length":5.03,"rotation":-6.7,"x":0.95,"y":-1.13},{"name":"bone27","parent":"root","x":-27.66,"y":130.11,"color":"ff0000ff"},{"name":"bone67","parent":"root","x":-55.12,"y":-42.68,"color":"ff0000ff"},{"name":"bone68","parent":"root","x":-56.16,"y":15.32,"color":"ff0000ff"}],"slots":[{"name":"1_x","bone":"bone27","color":"ffffff00","attachment":"1_x","blend":"additive"},{"name":"shadow","bone":"root","attachment":"shadow"},{"name":"weapon","bone":"bone46","attachment":"weapon"},{"name":"weapon3","bone":"bone57","attachment":"weapon"},{"name":"tay1","bone":"root","attachment":"tay1"},{"name":"tay1b","bone":"root","attachment":"tay1b"},{"name":"aoback","bone":"root","attachment":"aoback"},{"name":"chan1","bone":"root","attachment":"chan1"},{"name":"chan2","bone":"root","attachment":"chan2"},{"name":"pant","bone":"root","attachment":"pant"},{"name":"body1","bone":"root","attachment":"body1"},{"name":"body1 copy","bone":"root","attachment":"body1 copy"},{"name":"day","bone":"root","attachment":"day"},{"name":"weapon2","bone":"bone57","attachment":"weapon"},{"name":"tay33","bone":"root"},{"name":"head","bone":"root","attachment":"head"},{"name":"vai2","bone":"root","attachment":"vai2"},{"name":"tay22","bone":"root","attachment":"tay22"},{"name":"tay333","bone":"root","attachment":"tay333"},{"name":"aa_1","bone":"bone67","color":"ffffff00","attachment":"aa_1","blend":"additive"},{"name":"aa_2","bone":"bone67","color":"ffffff00","attachment":"aa_1"},{"name":"x_aa","bone":"bone68","color":"ffffff00","attachment":"x_aa","blend":"additive"},{"name":"x_aa2","bone":"bone68","color":"ffffff00","attachment":"x_aa"}],"skins":{"default":{"1_x":{"1_x":{"x":2.47,"y":-0.73,"scaleX":-1.9,"scaleY":1.9,"width":100,"height":97}},"aa_1":{"aa_1":{"x":24.53,"y":-7.36,"width":163,"height":119}},"aa_2":{"aa_1":{"x":24.53,"y":-7.36,"width":163,"height":119}},"aoback":{"aoback":{"type":"mesh","hull":10,"width":53,"height":48,"uvs":[1,0.55673,1,0.76044,0.82664,0.86109,0.58739,1,0.37511,1,0.15407,0.7426,0,0.5632,0,0.5559,0.25031,0.01887,0.62771,0.01973,0.58818,0.64898,0.34517,0.5081],"triangles":[11,8,9,7,8,11,10,11,9,5,6,7,11,5,7,4,11,10,5,11,4,0,10,9,2,10,0,1,2,0,3,4,10,2,3,10],"vertices":[1,41,8.02,21.84,1,1,41,17.05,18.08,1,1,41,17.97,7.74,1,2,41,19.25,-6.53,0.63807,40,24.92,9.9,0.36193,2,41,14.92,-16.92,0.02033,40,24.73,-1.35,0.97967,1,40,12.19,-12.86,1,1,40,3.44,-20.88,1,1,40,3.09,-20.87,1,2,41,-31.09,-4.91,0.06342,40,-22.46,-7.18,0.93658,2,41,-23.36,13.54,0.43158,40,-22.09,12.82,0.56842,1,41,3.71,-0.01,1,1,40,1.1,-2.54,1],"edges":[0,18,0,2,6,8,12,14,14,16,16,18,8,10,10,12,2,4,4,6]}},"body1":{"body1":{"type":"mesh","hull":12,"width":32,"height":48,"uvs":[0.80783,0.16097,1,0.29179,0.98109,0.54026,0.7972,0.85511,0.197,1,0.08548,1,0.04422,0.78166,0,0.54767,0,0.47856,0.09111,0.29424,0.17336,0.12786,0.6134,0.0286,0.25902,0.52898,0.6069,0.5668,0.28171,0.37521,0.6258,0.30967,0.24012,0.68275,0.5464,0.77855],"triangles":[15,14,10,12,8,14,13,14,15,7,8,12,16,7,12,6,7,16,17,16,13,6,4,5,16,4,6,16,17,4,4,17,3,12,14,13,16,12,13,3,13,2,17,13,3,14,9,10,8,9,14,15,11,0,15,0,1,2,15,1,13,15,2,10,11,15],"vertices":[4,13,4.56,-14.59,0.11751,20,4,14.34,0.02726,19,4.28,4.54,0.85522,25,-17.96,-12.43,0.00001,3,20,9.08,7.16,0.42153,19,9.35,-2.64,0.57846,22,19.38,-8.56,0.00001,4,20,6.59,-4.52,0.7311,19,6.86,-14.32,0.02548,22,7.44,-8.13,0.24329,21,1.77,-12.84,0.00013,2,22,-7.76,-2.48,0.82882,10,-2.01,-15.31,0.17118,3,22,-15,16.62,0.00093,10,-9.25,3.79,0.85251,23,-15.61,-1.27,0.14656,2,10,-9.3,7.36,0.81541,23,-15.66,2.29,0.18459,3,10,1.15,8.84,0.30032,23,-5.2,3.77,0.69753,24,-10.4,4.36,0.00215,3,23,6.01,5.36,0.1357,24,0.83,5.78,0.62335,26,1.82,7.24,0.24094,3,23,9.32,5.41,0.02415,24,4.15,5.78,0.42399,26,2.66,4.03,0.55186,3,13,-0.84,8.6,0.04526,25,2.62,-0.45,0.88384,26,2.07,-5.27,0.0709,3,13,7.03,5.62,0.74448,19,-15.52,9.33,0.00002,25,2.09,-8.84,0.2555,3,13,11.18,-8.65,0.57437,19,-0.86,11.8,0.42557,25,-10.33,-17.01,0.00006,3,24,1.73,-2.51,0.3395,26,-5.97,4.28,0.03371,11,4.37,2.08,0.62679,5,20,-5.44,-3.87,0.08343,19,-5.16,-13.68,0.00011,22,5.99,3.82,0.02897,21,0.5,-0.87,0.8798,12,-4,-9.59,0.00769,3,25,-4.26,1.77,0.1296,26,-4.81,-3.05,0.08119,12,3.89,1.83,0.7892,5,13,-2.32,-8.46,0.03351,20,-2.88,8.22,0.09629,19,-2.61,-1.59,0.6361,21,12.84,-1.47,0.0226,12,8.32,-8.73,0.21151,2,10,6,2.64,0.57102,23,-0.36,-2.42,0.42898,3,22,-4.2,5.6,0.41635,21,-9.67,1.07,0.06892,10,1.55,-7.23,0.51473],"edges":[2,4,4,6,6,8,8,10,14,16,20,22,16,18,18,20,2,0,0,22,10,12,12,14]}},"body1 copy":{"body1 copy":{"type":"mesh","hull":10,"width":35,"height":40,"uvs":[0.66069,0,0.88185,0.05527,1,0.18749,0.99754,0.32521,0.6957,0.81588,0.19794,0.97917,0.05847,0.84531,0.02194,0.38713,0.10696,0.1131,0.49172,0.00232,0.33157,0.55488,0.69032,0.52478,0.3414,0.29043,0.14238,0.50973,0.31192,0.79782],"triangles":[7,8,12,6,7,13,10,13,12,13,7,12,5,14,4,4,14,10,5,6,14,6,13,14,14,13,10,4,10,11,10,12,11,4,11,3,11,12,0,12,9,0,12,8,9,11,1,3,11,0,1,3,1,2],"vertices":[2,48,9.06,2.85,0.7135,12,14.51,-11.11,0.2865,3,48,7.78,-5.09,0.95092,12,13.24,-19.06,0.02864,47,17.2,-5.6,0.02044,2,48,3.02,-9.83,0.84017,47,11.92,-9.74,0.15983,2,48,-2.46,-10.4,0.63193,47,6.41,-9.65,0.36807,3,47,-13.22,0.91,0.11213,46,-4.44,-5.46,0.88127,10,-2.61,-14.16,0.00659,3,46,-11.24,11.86,0.02296,10,-9.41,3.17,0.57246,51,-10.27,-1.86,0.40458,2,10,-4.13,8.13,0.15551,51,-5,3.11,0.84449,4,51,13.31,4.66,0.01329,50,3.8,5.72,0.57382,49,-5.31,5.38,0.38163,11,5.28,9.6,0.03126,3,12,7.72,7.6,0.2887,50,14.76,2.74,0.00094,49,5.92,3.72,0.71036,2,48,8.27,8.71,0.36828,12,13.72,-5.25,0.63172,5,48,-14.34,11.66,0.00041,47,-2.78,13.66,0.01101,46,5.8,7.44,0.02954,10,7.63,-1.25,0.8317,11,-1.43,-1.23,0.12734,4,47,-1.58,1.1,0.82792,46,7.2,-5.09,0.13512,10,9.03,-13.79,0.00339,11,-0.22,-13.79,0.03357,5,48,-3.8,12.57,0.0217,12,1.65,-1.39,0.73895,47,7.8,13.31,0.00836,46,16.38,7.26,0.00016,11,9.15,-1.58,0.23083,4,10,9.34,5.39,0.01545,51,8.47,0.37,0.09293,50,-1.1,1.5,0.88202,49,-9.68,0.61,0.0096,3,46,-3.93,7.99,0.08664,10,-2.09,-0.71,0.87829,51,-2.96,-5.74,0.03507],"edges":[0,18,0,2,2,4,4,6,6,8,8,10,10,12,12,14,14,16,16,18]}},"chan1":{"chan1":{"type":"mesh","hull":14,"width":39,"height":71,"uvs":[0.8511,0,0.99999,0.08241,0.99999,0.22389,0.65471,0.46743,0.65538,0.83492,0.68763,0.95373,0.22043,1,0.15282,1,0,0.91834,0,0.83112,0.30286,0.84276,0.10666,0.51064,0.15814,0.40134,0.62452,0],"triangles":[8,9,10,7,8,10,6,7,10,5,6,10,10,11,3,3,4,10,5,10,4,13,2,3,1,13,0,2,13,1,12,13,3,11,12,3],"vertices":[1,36,-9.18,4.22,1,1,36,-6.28,11.93,1,1,36,2.85,16.11,1,2,36,24.18,11.07,0.7165,37,1.31,13.01,0.2835,2,37,26.71,7.03,0.99175,38,-7.24,0.15,0.00825,2,37,35.21,6.31,0.52135,38,-4.31,8.16,0.47865,2,38,13.26,2.32,0.00835,39,4.6,4.22,0.99165,1,39,7.21,3.86,1,1,39,12.32,-2.7,1,1,39,11.47,-8.83,1,3,37,24.09,-6.48,0.40187,38,5.09,-5.95,0.36569,39,-0.11,-6.4,0.23244,2,36,35.87,-7.09,0.20473,37,-0.62,-8.5,0.79527,2,36,27.98,-8.49,0.94011,37,-7.71,-4.76,0.05989,1,36,-5.5,-3.82,1],"edges":[0,26,0,2,2,4,10,12,12,14,14,16,24,26,8,10,4,6,6,8,22,24,16,18,18,20,20,22]}},"chan2":{"chan2":{"type":"mesh","hull":16,"width":45,"height":93,"uvs":[0.82444,0.32759,0.81118,0.40595,0.90896,0.82986,1,0.93162,1,0.9734,0.80735,1,0.68696,0.98441,0.60514,0.87356,0.60042,0.80681,0.34995,0.47543,0.30843,0.42243,0.002,0.16416,0.00001,0.06548,0.11049,0,0.41589,0,0.42159,0.00002,0.55073,0.3878,0.77614,0.8154,0.79045,0.94005],"triangles":[6,18,5,5,18,4,6,7,18,18,3,4,7,17,18,18,2,3,18,17,2,7,8,17,2,17,1,17,8,1,8,9,1,1,9,16,9,10,16,15,16,14,14,16,11,11,16,10,14,11,13,1,16,0,16,15,0,11,12,13],"vertices":[2,33,30.21,14.37,0.84506,34,-6.47,13,0.15494,2,33,36.16,10.12,0.42508,34,0.51,10.83,0.57492,2,34,39.95,6.58,0.22251,35,3.54,5.74,0.77749,1,35,13.75,4.29,1,1,35,17.06,2.26,1,1,35,14.65,-6.42,1,1,35,10.58,-10.29,1,2,34,40.95,-7.65,0.35295,35,-0.13,-8.05,0.64705,2,34,34.85,-6.51,0.95634,35,-5.54,-4.99,0.04366,2,33,31.07,-11.01,0.42465,34,2.32,-10.83,0.57535,2,33,25.88,-10.09,0.83508,34,-2.9,-11.58,0.16492,1,33,-1.81,-9.62,1,1,33,-9.74,-4.99,1,1,33,-12.42,2.4,1,1,33,-5.37,14.2,1,1,33,-5.24,14.42,1,2,33,28.7,0.93,0.98923,34,-3.68,-0.24,0.01077,2,34,37.34,1.03,0.85722,35,-0.73,1.34,0.14278,1,35,9.5,-4.16,1],"edges":[0,30,8,10,10,12,22,24,24,26,26,28,28,30,6,8,0,2,18,20,20,22,16,18,2,4,4,6,12,14,14,16]}},"day":{"day":{"type":"mesh","hull":15,"width":14,"height":52,"uvs":[0.92977,0.28652,0.92983,0.43503,0.92991,0.63977,0.85925,0.77875,0.93003,0.95093,0.33088,0.99999,0.07787,1,0.03666,0.92244,0.07593,0.76439,0.11518,0.6064,0.2932,0.40751,0.20366,0.25024,0.26583,0,0.60482,0,0.92966,0.01891,0.56978,0.41633,0.53685,0.61052,0.52014,0.75677,0.50342,0.89852],"triangles":[7,8,18,18,3,4,5,7,18,5,18,4,6,7,5,8,9,17,3,17,2,18,8,17,18,17,3,15,10,11,15,0,1,16,10,15,16,15,1,9,10,16,16,1,2,17,9,16,17,16,2,11,12,13,0,13,14,13,0,11,0,15,11],"vertices":[2,57,3.12,3.79,0.95443,56,10.6,3.96,0.04557,3,57,10.8,4.6,0.2812,59,-5.87,4.41,0.00573,58,0.93,4.57,0.71307,3,59,4.73,5.47,0.73475,58,11.55,5.33,0.01343,60,-1.4,5.63,0.25183,3,59,12.02,5.2,0.01105,60,5.82,4.64,0.65553,61,-1.4,4.54,0.33342,1,61,7.44,6.28,1,1,61,10.68,-1.87,1,2,60,17.33,-6.29,0.00001,61,10.98,-5.4,0.99999,2,60,13.3,-6.87,0.03772,61,7,-6.31,0.96228,3,59,12.36,-5.79,0.01907,60,5.08,-6.32,0.72378,61,-1.23,-6.45,0.25715,3,59,4.13,-6.06,0.79015,58,10.63,-6.17,0.05293,60,-3.14,-5.77,0.15691,3,57,10.31,-4.41,0.42902,59,-6.4,-4.61,0.00459,58,0.13,-4.42,0.5664,2,57,2.31,-6.51,0.77274,56,10.37,-6.37,0.22726,1,56,-2.61,-7.6,1,1,56,-3.37,-2.92,1,1,56,-3.13,1.73,1,2,57,10.36,-0.52,0.15822,58,0.32,-0.53,0.84178,1,59,3.76,-0.16,1,2,60,4.68,-0.1,0.9999,61,-2.14,-0.28,0.0001,1,61,5.22,0.1,1],"edges":[8,10,10,12,12,14,24,26,26,28,8,6,6,4,4,2,20,22,22,24,18,20,14,16,16,18,2,0,0,28]}},"head":{"head":{"type":"mesh","hull":8,"width":20,"height":24,"uvs":[0.55123,0.04112,0.90151,0.33397,0.90221,0.62482,0.73916,0.96246,0.31487,0.95803,0.04942,0.62662,0.04741,0.46116,0.29988,0.03712],"triangles":[1,5,6,2,5,1,0,6,7,6,0,1,4,5,2,3,4,2],"vertices":[1,13,23.36,-2.07,1,1,13,16.03,-8.77,1,1,13,9.06,-8.48,1,1,13,1.11,-4.87,1,1,13,1.58,3.61,1,1,13,9.76,8.56,1,1,13,13.73,8.43,1,1,13,23.67,2.94,1],"edges":[0,14,0,2,2,4,4,6,6,8,8,10,10,12,12,14]}},"pant":{"pant":{"type":"mesh","hull":23,"width":80,"height":61,"uvs":[0.39848,0,0.54347,0.0119,0.6742,0.12281,0.81953,0.38506,0.99999,0.71469,0.97881,0.77441,0.74657,0.74117,0.62009,0.61137,0.51984,0.43494,0.57797,0.66267,0.53046,0.83845,0.39489,1,0.34972,1,0.25925,0.82113,0.24249,0.61987,0.29893,0.45874,0.24186,0.58723,0.15334,0.74781,0.00001,0.77829,0,0.71706,0.13401,0.40906,0.22599,0.19765,0.29116,0.04788,0.37044,0.77935,0.38281,0.54889,0.39395,0.31356,0.39147,0.14802,0.53874,0.21781,0.66867,0.35414,0.78623,0.53104,0.30361,0.2876],"triangles":[15,20,30,16,20,15,17,19,20,16,17,20,18,19,17,23,24,9,23,13,14,10,23,9,11,23,10,12,13,23,11,12,23,24,14,15,24,8,9,23,14,24,29,3,4,6,7,29,6,29,4,5,6,4,29,28,3,7,8,28,7,28,29,26,22,0,21,22,26,30,21,26,20,21,30,25,26,27,30,26,25,8,25,27,15,30,25,24,15,25,24,25,8,26,0,1,27,26,1,27,1,2,28,27,2,28,2,3,8,27,28],"vertices":[3,5,-15.42,-4.25,0.28871,2,-13.43,-0.8,0.39398,8,-13.65,2.4,0.31731,3,5,-8.14,4.81,0.86482,2,-14,10.81,0.11304,8,-18.39,13.01,0.02215,1,5,3.42,9.45,1,3,5,23.19,9.73,0.08406,6,9.22,7.9,0.78341,7,-3.06,8.04,0.13253,1,7,20.82,1.5,1,1,7,21.8,-2.39,1,2,6,19.23,-12.24,0.22833,7,6.08,-12.51,0.77167,4,5,25.27,-11.27,0.00701,2,21.66,20.96,0.01572,6,6.41,-13.01,0.84354,7,-6.76,-12.73,0.13373,5,5,11.85,-11.62,0.28106,2,11.86,11.8,0.48015,6,-6.73,-10.26,0.17107,3,-7.15,12.24,0.0645,4,-18.02,11.44,0.00321,5,5,25.88,-15.83,0.01221,2,25.14,17.96,0.20641,6,5.96,-17.58,0.00253,3,6.47,17.62,0.49051,4,-4.65,17.42,0.28833,4,5,32.45,-25.12,0.00003,2,36.22,15.38,0.02781,3,17.38,14.39,0.2167,4,6.39,14.69,0.75546,1,4,17.26,4.86,1,1,4,17.61,1.26,1,2,3,17.47,-7.34,0.04843,4,7.46,-7.01,0.95157,3,2,25.53,-9,0.05675,3,5.28,-9.32,0.84436,4,-4.62,-9.54,0.09889,4,2,15.26,-5.6,0.59068,8,14.84,8.34,0.20412,3,-4.77,-5.33,0.04452,9,-1.61,8.25,0.16067,3,2,23.56,-9.27,0.03897,8,23.9,7.93,0.00921,9,7.46,8.41,0.95182,1,9,19.5,7.44,1,1,9,27.45,-2.09,1,1,9,24.26,-4.03,1,2,8,18.28,-4.76,0.1361,9,2.64,-4.6,0.8639,1,8,3.44,-4.23,1,3,5,-17.99,-12.95,0.03971,2,-9.57,-9.01,0.1592,8,-7.07,-3.85,0.80109,3,2,34.06,2.26,0.00042,3,14.46,1.41,0.0108,4,4.06,1.6,0.98878,4,5,11.21,-24.58,0.00363,2,19.98,1.68,0.41901,6,-10.34,-22.73,0.00103,3,0.37,1.66,0.57632,3,5,-0.01,-15.57,0.01799,2,5.62,0.97,0.98155,6,-19.18,-11.38,0.00046,3,5,-8.37,-9.91,0.12219,2,-4.4,-0.35,0.65849,8,-5.39,6.09,0.21932,2,5,1.9,-2.74,0.86068,2,-1.47,11.83,0.13932,2,5,14.69,0.95,0.77752,6,-1.07,1.32,0.22248,2,6,13.12,-0.53,0.28607,7,0.48,-0.55,0.71393,2,2,4.85,-6.39,0.3453,8,5.42,3.82,0.6547],"edges":[0,44,0,2,2,4,8,10,36,38,34,36,20,22,18,20,16,18,14,16,10,12,12,14,4,6,6,8,38,40,22,24,24,26,26,28,28,30,30,32,32,34,40,42,42,44]}},"shadow":{"shadow":{"type":"mesh","hull":8,"width":106,"height":79,"uvs":[0.99575,0.70032,0.84594,0.93365,0.4571,0.71495,0.1034,0.51602,0,0.08473,0.23524,0.08728,0.46276,0.17877,0.66559,0.26033],"triangles":[3,4,5,6,3,5,2,3,6,2,6,7,1,2,7,0,1,7],"vertices":[1,63,33.84,14.38,1,2,63,38.92,-9.42,0.99344,64,57.02,29.37,0.00656,3,63,0.24,-31.8,0.47321,64,28.14,-4.74,0.00312,62,42.22,20.48,0.52366,1,62,17.35,-11.68,1,1,62,-18.4,-13.47,1,1,62,-11.77,10.56,1,3,63,-33.15,-5.72,0.35274,64,-12.08,8.59,0.17595,62,1.45,32,0.47131,2,63,-15.01,7.52,0.66719,64,0.54,27.15,0.33281],"edges":[0,14,0,2,6,8,8,10,2,4,4,6,10,12,12,14]}},"tay1":{"tay1":{"type":"mesh","hull":10,"width":28,"height":55,"uvs":[1,0.0022,0.93024,0.66592,0.84304,0.79593,0.12198,0.99999,0.00001,0.98178,0.02785,0.80485,0.36278,0.60753,0.26349,0.38426,0.39658,0.09012,0.80132,0.00001],"triangles":[4,5,3,2,3,5,2,5,6,2,6,1,7,0,1,9,0,7,1,6,7,9,7,8],"vertices":[1,42,-18.41,8.78,1,2,42,18.03,11.65,0.55237,43,-3.9,11.03,0.44763,3,42,25.44,10.17,0.15625,43,3.45,12.77,0.84308,44,-9.85,14.68,0.00067,1,44,8.2,0.26,1,1,44,8.57,-3.28,1,2,43,16.02,-6.29,0.28766,44,-0.73,-6.25,0.71234,2,42,16.94,-4.52,0.49973,43,1.84,-4.13,0.50027,1,42,5.13,-8.89,1,1,42,-11.4,-7.33,1,1,42,-17.8,3.25,1],"edges":[0,18,0,2,2,4,4,6,6,8,8,10,16,18,14,16,10,12,12,14]}},"tay1b":{"tay1b":{"type":"mesh","hull":7,"width":12,"height":15,"uvs":[0.86636,0.06645,0.96508,0.83438,0.33108,1,0.18122,1,0,0.63367,0,0.52444,0.29284,0.06431],"triangles":[1,2,4,0,1,5,0,5,6,1,4,5,3,4,2],"vertices":[1,65,-4.37,2.16,1,1,65,5.13,8.79,1,1,65,10.99,3.34,1,1,65,11.86,1.76,1,1,65,8.11,-2.8,1,1,65,6.68,-3.6,1,1,65,-1.06,-3.87,1],"edges":[0,12,0,2,2,4,4,6,6,8,8,10,10,12]}},"tay22":{"tay22":{"type":"mesh","hull":10,"width":19,"height":16,"uvs":[0.47873,0.37283,0.4902,0.00002,0.66279,0.00001,0.76801,0.1934,0.99999,0.61978,0.84403,1,0.4345,0.90594,0.0474,0.81442,0.0504,0.62523,0.41347,0.559],"triangles":[6,7,9,7,8,9,5,6,4,0,4,9,0,3,4,4,6,9,3,0,2,0,1,2],"vertices":[3,30,4.82,4.6,0.74985,31,2.62,-5.73,0.21895,32,-0.87,-5.86,0.0312,2,30,10.78,4.38,0.99819,31,1.99,-11.67,0.00181,1,30,10.78,1.1,1,1,30,7.69,-0.9,1,2,30,0.86,-5.3,0.99992,31,-6.98,-1.1,0.00008,2,30,-5.22,-2.34,0.62486,31,-3.6,4.76,0.37514,2,31,4.06,2.72,0.5484,32,-0.35,2.7,0.4516,1,32,7.06,1.51,1,1,32,7.11,-1.52,1,3,30,1.84,5.84,0.16017,31,4.07,-2.85,0.38675,32,0.26,-2.84,0.45309],"edges":[2,4,8,10,10,12,12,14,14,16,16,18,2,0,0,18,4,6,6,8]}},"tay33":{"tay33":{"type":"mesh","hull":10,"width":45,"height":34,"uvs":[0.02117,0.08498,0.52686,0.08978,0.76591,0.41739,1,0.82713,1,0.92814,0.9037,0.99081,0.5517,0.82431,0.36299,0.70739,0.23102,0.74729,0.02176,0.50032],"triangles":[4,5,3,3,5,2,5,6,2,6,7,2,8,9,7,7,1,2,7,9,1,9,0,1],"vertices":[1,15,-10.15,7.12,1,1,15,11.97,12.48,1,2,15,25.11,4.28,0.28509,16,2.13,6.39,0.71491,2,16,19.47,4.3,0.02709,17,6.34,3.86,0.97291,1,17,8.64,1.31,1,1,17,6.85,-3.18,1,3,15,19.11,-11.48,0.24886,16,5.4,-10.16,0.75081,17,-8.72,-9.56,0.00033,2,15,9.91,-9.68,0.85986,16,-3.35,-13.51,0.14014,2,15,4.48,-12.44,0.97727,16,-6.5,-18.73,0.02273,1,15,-6.69,-6.57,1],"edges":[0,18,0,2,2,4,4,6,6,8,8,10,10,12,12,14,14,16,16,18]}},"tay333":{"tay333":{"type":"mesh","hull":9,"width":24,"height":57,"uvs":[0.78017,0.0497,0.9826,0.24207,0.83102,0.56748,0.68624,0.87831,0.55181,0.99283,0.20851,0.96916,0.11284,0.52551,0.03404,0.16006,0.45146,0.02833],"triangles":[4,5,3,5,6,3,3,6,2,1,2,8,7,8,2,1,8,0,2,6,7],"vertices":[1,52,-9.69,4.96,1,1,52,1.02,10.35,1,2,52,19.72,7.62,0.98446,53,-0.78,7.69,0.01554,3,52,37.59,5.02,0.00541,53,17.25,6.66,0.33782,54,2.61,6.52,0.65677,2,53,24.15,4.35,0.00438,54,9.37,3.81,0.99562,2,53,23.93,-4,0.0019,54,8.67,-4.51,0.9981,2,52,18.18,-9.71,0.16273,53,-0.81,-9.71,0.83727,2,52,-2.53,-12.62,0.98805,53,-21.19,-14.41,0.01195,1,52,-10.52,-2.98,1],"edges":[0,16,0,2,6,8,8,10,14,16,10,12,12,14,2,4,4,6]}},"vai2":{"vai2":{"type":"mesh","hull":6,"width":34,"height":40,"uvs":[0.97583,0.62454,0.96951,0.97646,0.58383,0.9759,0.02815,0.54403,0.0282,0.1428,0.4589,0.01007],"triangles":[2,3,0,1,2,0,5,3,4,5,0,3],"vertices":[2,28,22.54,8.81,0.20233,29,4.93,10.63,0.79767,1,29,15.35,1.18,1,2,28,18.79,-10.19,0.05202,29,6.68,-8.66,0.94798,1,28,-6.41,-5.68,1,1,28,-14.99,7.89,1,1,28,-5.45,20.2,1],"edges":[0,10,0,2,2,4,4,6,6,8,8,10]}},"weapon":{"weapon":{"type":"mesh","hull":7,"width":140,"height":123,"uvs":[1,0.00696,1,0.03798,0.25813,0.81489,0.11559,1,0.00808,1,0,0.88037,0.93977,0],"triangles":[6,0,1,2,6,1,6,2,5,3,4,5,2,3,5],"vertices":[-73.82,36.99,-70.29,38.44,57.54,-21.38,86.18,-31.2,91.9,-45.13,78.71,-51.76,-71.41,28.86],"edges":[0,12,0,2,2,4,4,6,6,8,8,10,10,12]}},"weapon2":{"weapon":{"type":"mesh","hull":7,"width":140,"height":123,"uvs":[0.81428,0.18169,0.81529,0.22138,0.25813,0.81489,0.11559,1,0.00808,1,0,0.88037,0.76466,0.17421],"triangles":[1,2,6,1,6,0,6,2,5,3,4,5,2,3,5],"vertices":[-49.45,2.17,-46.15,5.78,60.66,3.88,90.84,6.34,101.64,-4.14,92.21,-15.49,-45.1,-3.32],"edges":[0,12,0,2,2,4,4,6,6,8,8,10,10,12]}},"weapon3":{"weapon":{"type":"mesh","hull":7,"width":140,"height":123,"uvs":[1,0,1,0.05013,0.76778,0.28925,0.69259,0.3307,0.67428,0.29662,0.69781,0.22865,0.93629,0],"triangles":[6,0,1,2,5,6,2,6,1,4,5,2,3,4,2],"vertices":[-83.69,4.23,-79.38,8.66,-35.56,7.14,-24.46,3.47,-25.54,-1.32,-33.72,-5.03,-77.26,-1.98],"edges":[0,12,0,2,2,4,4,6,6,8,8,10,10,12]}},"x_aa":{"x_aa":{"x":24.98,"y":69.16,"scaleX":1.5,"scaleY":1.5,"rotation":37.1,"width":96,"height":64}},"x_aa2":{"x_aa":{"x":24.98,"y":69.16,"scaleX":1.5,"scaleY":1.5,"rotation":37.1,"width":96,"height":64}}}},"animations":{"Attack":{"slots":{"1_x":{"color":[{"time":0.1667,"color":"ffffff00"},{"time":0.2667,"color":"ffffffff"},{"time":0.5,"color":"ffffffba"},{"time":0.6,"color":"ffffff00"}]},"aa_1":{"color":[{"time":0.7,"color":"ffffff00"},{"time":0.7333,"color":"ffffffff","curve":"stepped"},{"time":0.8,"color":"ffffffff"},{"time":0.8333,"color":"ffffff00"}]},"aa_2":{"color":[{"time":0.7,"color":"ffffff00"},{"time":0.7333,"color":"ffffff3c"},{"time":0.8,"color":"ffffff51"},{"time":0.8333,"color":"ffffff00"}]},"body1":{"color":[{"time":0.6667,"color":"ffffffff"},{"time":0.7333,"color":"ffffff00","curve":"stepped"},{"time":0.8667,"color":"ffffff00"},{"time":1.1,"color":"ffffffff"}]},"body1 copy":{"color":[{"time":0,"color":"ffffff00","curve":"stepped"},{"time":0.6333,"color":"ffffff00"},{"time":0.7,"color":"ffffffff","curve":"stepped"},{"time":0.9,"color":"ffffffff"},{"time":1.2,"color":"ffffff00"}],"attachment":[{"time":0,"name":null},{"time":0.5,"name":"body1 copy"},{"time":1.2,"name":null}]},"tay1":{"attachment":[{"time":0.7,"name":null},{"time":1.2,"name":"tay1"}]},"tay1b":{"attachment":[{"time":0.7,"name":null},{"time":1.2,"name":"tay1b"}]},"tay22":{"attachment":[{"time":0.7,"name":null},{"time":1.2,"name":"tay22"}]},"tay33":{"attachment":[{"time":0.7,"name":"tay33"},{"time":1.2,"name":null}]},"tay333":{"attachment":[{"time":0,"name":null},{"time":0.7,"name":"tay333"},{"time":1.2,"name":null}]},"vai2":{"attachment":[{"time":0.7,"name":null},{"time":1.2,"name":"vai2"}]},"weapon":{"attachment":[{"time":0.7,"name":null},{"time":1.2,"name":"weapon"}]},"weapon2":{"attachment":[{"time":0,"name":null},{"time":0.7,"name":"weapon"},{"time":1.2,"name":null}]},"weapon3":{"attachment":[{"time":0,"name":null},{"time":0.7,"name":"weapon"},{"time":1.2,"name":null}]},"x_aa":{"color":[{"time":0.6,"color":"ffffff00"},{"time":0.7,"color":"ffffffff"},{"time":0.7333,"color":"ffffff00"}]},"x_aa2":{"color":[{"time":0.6,"color":"ffffff00"},{"time":0.7,"color":"ffffff4f"},{"time":0.7333,"color":"ffffff00"}]}},"bones":{"bone27":{"rotate":[{"time":0.1667,"angle":0},{"time":0.3,"angle":176.13},{"time":0.4333,"angle":-58.83},{"time":0.5333,"angle":56.18},{"time":0.6,"angle":139.7}]},"bone67":{"translate":[{"time":0.7,"x":1.17,"y":51.48},{"time":0.8,"x":-58.76,"y":-107.81}],"scale":[{"time":0.7,"x":0.48,"y":0.865},{"time":0.8,"x":0.893,"y":1.328}],"shear":[{"time":0.7,"x":53.74,"y":11.28},{"time":0.8,"x":58.76,"y":12.33}]},"bone46":{"rotate":[{"time":0.1667,"angle":0},{"time":0.2333,"angle":81.63},{"time":0.3,"angle":170.55},{"time":0.3667,"angle":-116.6},{"time":0.4333,"angle":-74.43},{"time":0.4667,"angle":-43.38},{"time":0.5667,"angle":-49.93},{"time":0.6667,"angle":25.13,"curve":"stepped"},{"time":0.9,"angle":25.13},{"time":1.3333,"angle":0}],"translate":[{"time":0,"x":0,"y":0},{"time":0.1667,"x":15.2,"y":-7.43},{"time":0.4333,"x":16.68,"y":7.46},{"time":0.4667,"x":10.1,"y":5.41},{"time":0.6667,"x":11.24,"y":-7.33},{"time":0.9,"x":15.2,"y":-7.43},{"time":1.3333,"x":0,"y":0}]},"bone57":{"translate":[{"time":0,"x":0,"y":0},{"time":0.7,"x":-20.95,"y":2.45},{"time":0.9,"x":-23.31,"y":2.67},{"time":1.3333,"x":0,"y":0}]},"bone68":{"rotate":[{"time":0.6333,"angle":-25.71},{"time":0.6667,"angle":12.82},{"time":0.7,"angle":11.87}],"translate":[{"time":0.6333,"x":-79.86,"y":77.18},{"time":0.6667,"x":-39.01,"y":-34.61},{"time":0.7,"x":-5.28,"y":-57.45}],"scale":[{"time":0.6333,"x":0.656,"y":0.717},{"time":0.6667,"x":1,"y":1}],"shear":[{"time":0.6333,"x":0,"y":-17.34},{"time":0.6667,"x":12.52,"y":-2.2},{"time":0.7,"x":25.04,"y":12.95}]},"bone":{"translate":[{"time":0,"x":0,"y":0},{"time":0.1667,"x":0,"y":-4.76,"curve":"stepped"},{"time":0.6,"x":0,"y":-4.76},{"time":0.7667,"x":-0.26,"y":-21.16,"curve":"stepped"},{"time":0.9,"x":-0.26,"y":-21.16},{"time":1.3333,"x":0,"y":0}]},"bone2":{"rotate":[{"time":0,"angle":0},{"time":0.1667,"angle":-7.31,"curve":"stepped"},{"time":0.6667,"angle":-7.31},{"time":0.7667,"angle":-16.71},{"time":0.9,"angle":-7.31},{"time":1.3333,"angle":0}],"translate":[{"time":0,"x":0,"y":0},{"time":0.1667,"x":-1.76,"y":0,"curve":"stepped"},{"time":0.9,"x":-1.76,"y":0},{"time":1.3333,"x":0,"y":0}]},"bone3":{"rotate":[{"time":0.6667,"angle":0},{"time":0.7667,"angle":-12.51},{"time":0.9,"angle":0}]},"bone4":{"rotate":[{"time":0.6667,"angle":0},{"time":0.7667,"angle":-12.51},{"time":0.9,"angle":0}]},"bone5":{"rotate":[{"time":0,"angle":0},{"time":0.1667,"angle":-11.5,"curve":"stepped"},{"time":0.6,"angle":-11.5},{"time":0.7667,"angle":1.67},{"time":0.9,"angle":-5},{"time":1.3333,"angle":0}]},"bone6":{"rotate":[{"time":0,"angle":0,"curve":[0.25,0,0.75,1]},{"time":0.1667,"angle":-1.85,"curve":"stepped"},{"time":0.6,"angle":-1.85},{"time":0.7667,"angle":9.89},{"time":0.9,"angle":-1.56},{"time":1.3333,"angle":0}]},"bone7":{"rotate":[{"time":0,"angle":0,"curve":[0.243,0,0.658,0.64]},{"time":0.6,"angle":2.8,"curve":[0.352,0.41,0.689,0.76]},{"time":0.7667,"angle":17.78,"curve":[0.367,0.63,0.705,1]},{"time":0.9,"angle":0}]},"bone8":{"rotate":[{"time":0,"angle":0,"curve":[0.25,0,0.75,1]},{"time":0.1667,"angle":-12.51,"curve":"stepped"},{"time":0.6,"angle":-12.51},{"time":0.7667,"angle":-38.53},{"time":0.9,"angle":-31.39},{"time":1.3333,"angle":0}]},"bone9":{"rotate":[{"time":0.6,"angle":0},{"time":0.7667,"angle":-3.14},{"time":0.9,"angle":5.98},{"time":1.3333,"angle":0}]},"bone11":{"rotate":[{"time":0,"angle":0},{"time":0.1667,"angle":-15.71},{"time":0.4,"angle":-19.09},{"time":0.5333,"angle":5.96,"curve":"stepped"},{"time":0.9,"angle":5.96},{"time":1.3333,"angle":0}]},"bone12":{"rotate":[{"time":0,"angle":0},{"time":0.1667,"angle":-4.73},{"time":0.5333,"angle":-5.87,"curve":"stepped"},{"time":0.9,"angle":-5.87},{"time":1.3333,"angle":0}]},"bone13":{"rotate":[{"time":0,"angle":0},{"time":0.1667,"angle":10.58,"curve":"stepped"},{"time":0.9,"angle":10.58},{"time":1.3333,"angle":0}],"translate":[{"time":0,"x":0,"y":0},{"time":0.6333,"x":-0.37,"y":-0.04},{"time":0.6667,"x":0.01,"y":-0.92},{"time":0.7,"x":-7.96,"y":-2.18},{"time":0.9,"x":-8.78,"y":-2.88},{"time":1.1,"x":-7.02,"y":-2.31},{"time":1.2,"x":-1.49,"y":-1.28},{"time":1.3333,"x":0,"y":0}]},"bone17":{"rotate":[{"time":0.7,"angle":0},{"time":0.7667,"angle":32.67},{"time":0.9,"angle":13.34},{"time":1.3333,"angle":0}],"translate":[{"time":0.7,"x":0,"y":0},{"time":0.7667,"x":-0.12,"y":1.47},{"time":0.9,"x":0,"y":0}]},"bone18":{"rotate":[{"time":0,"angle":0},{"time":0.7667,"angle":-8.94,"curve":"stepped"},{"time":0.9,"angle":-8.94},{"time":1.3333,"angle":0}]},"bone22":{"translate":[{"time":0.6333,"x":0,"y":0},{"time":0.8,"x":1.64,"y":-0.27,"curve":"stepped"},{"time":0.9,"x":1.64,"y":-0.27},{"time":1.3333,"x":0,"y":0}]},"bone29":{"rotate":[{"time":0,"angle":0,"curve":[0.25,0,0.75,1]},{"time":0.1667,"angle":-11.64},{"time":0.5333,"angle":2.18,"curve":"stepped"},{"time":0.6333,"angle":2.18},{"time":0.7667,"angle":16.65,"curve":"stepped"},{"time":0.9,"angle":16.65},{"time":1.3333,"angle":0}],"translate":[{"time":0,"x":0,"y":0},{"time":0.1667,"x":-4.43,"y":-2.68},{"time":0.4,"x":-5.1,"y":-2.81},{"time":0.5333,"x":-1.79,"y":-2.7,"curve":"stepped"},{"time":0.6333,"x":-1.79,"y":-2.7},{"time":0.7667,"x":1.71,"y":-3.27,"curve":"stepped"},{"time":0.9,"x":1.71,"y":-3.27},{"time":1.3333,"x":0,"y":0}]},"bone25":{"translate":[{"time":0.5667,"x":0,"y":0},{"time":0.7,"x":-1.22,"y":4.72},{"time":0.9,"x":0,"y":0}]},"bone26":{"translate":[{"time":0,"x":0,"y":0},{"time":0.1667,"x":3.7,"y":-5.27},{"time":0.4,"x":2.24,"y":-6.29,"curve":"stepped"},{"time":0.9,"x":2.24,"y":-6.29},{"time":1.3333,"x":0,"y":0}]},"bone43":{"rotate":[{"time":0,"angle":0,"curve":[0.25,0,0.75,1]},{"time":0.1667,"angle":-118.82},{"time":0.4333,"angle":-141.96},{"time":0.5333,"angle":-155.89},{"time":0.6667,"angle":-41.48,"curve":"stepped"},{"time":0.9,"angle":-41.48},{"time":1.3333,"angle":0}],"translate":[{"time":0,"x":0,"y":0,"curve":[0.25,0,0.75,1]},{"time":0.1667,"x":-1.38,"y":-1.51},{"time":0.4333,"x":-3.14,"y":-2.75},{"time":0.5333,"x":-1.39,"y":-2.29},{"time":0.6667,"x":-0.43,"y":1.16},{"time":0.9,"x":-0.34,"y":-2.02},{"time":1.3333,"x":0,"y":0}]},"bone44":{"rotate":[{"time":0,"angle":0,"curve":[0.25,0,0.75,1]},{"time":0.1667,"angle":4.63},{"time":0.4667,"angle":5.36},{"time":0.5667,"angle":4.04},{"time":0.6667,"angle":47.51,"curve":"stepped"},{"time":0.9,"angle":47.51},{"time":1.3333,"angle":0}],"translate":[{"time":0,"x":0,"y":0,"curve":[0.25,0,0.75,1]},{"time":0.1667,"x":-4.82,"y":-0.17},{"time":0.4333,"x":-1.02,"y":0.42,"curve":"stepped"},{"time":0.9,"x":-1.02,"y":0.42},{"time":1.3333,"x":0,"y":0}]},"bone45":{"rotate":[{"time":0,"angle":0,"curve":[0.25,0,0.75,1]},{"time":0.1667,"angle":-43.21},{"time":0.4667,"angle":-9.11},{"time":0.5333,"angle":2.26},{"time":0.6333,"angle":-23.03,"curve":"stepped"},{"time":0.9,"angle":-23.03},{"time":1.3333,"angle":0}]},"bone53":{"rotate":[{"time":0,"angle":0},{"time":0.7,"angle":-15.44},{"time":0.7667,"angle":0,"curve":"stepped"},{"time":0.9,"angle":0},{"time":1.2667,"angle":-21.41},{"time":1.3333,"angle":0}],"translate":[{"time":0.9,"x":0,"y":0},{"time":1.2667,"x":0.48,"y":-1.84},{"time":1.3333,"x":0,"y":0}]},"bone49":{"translate":[{"time":0.7,"x":0,"y":0},{"time":0.7667,"x":1.95,"y":-2.36},{"time":0.9,"x":0,"y":0}]},"bone14":{"translate":[{"time":0.6333,"x":0,"y":0},{"time":0.8,"x":0.13,"y":-0.91,"curve":"stepped"},{"time":0.9,"x":0.13,"y":-0.91},{"time":1.3333,"x":0,"y":0}]},"bone24":{"translate":[{"time":0.5667,"x":0,"y":0},{"time":0.7,"x":-4.85,"y":0.51},{"time":0.9,"x":0,"y":0}]},"bone48":{"translate":[{"time":0.7,"x":0,"y":0},{"time":0.7667,"x":0.33,"y":-0.41},{"time":0.9,"x":0,"y":0}]},"bone15":{"translate":[{"time":0.6333,"x":0,"y":0},{"time":0.8,"x":0.01,"y":-0.67,"curve":"stepped"},{"time":0.9,"x":0.01,"y":-0.67},{"time":1.3333,"x":0,"y":0}]},"bone23":{"translate":[{"time":0.5667,"x":0,"y":0},{"time":0.7,"x":-4.88,"y":-0.07},{"time":0.9,"x":0,"y":0}]},"bone34":{"rotate":[{"time":0,"angle":0,"curve":[0.25,0,0.75,1]},{"time":0.1667,"angle":-13.89,"curve":"stepped"},{"time":0.6,"angle":-13.89},{"time":0.7667,"angle":-6.72,"curve":"stepped"},{"time":0.9,"angle":-6.72},{"time":1.3333,"angle":0}],"translate":[{"time":0,"x":0,"y":0,"curve":[0.25,0,0.75,1]},{"time":0.1667,"x":-0.86,"y":3.73,"curve":"stepped"},{"time":0.9,"x":-0.86,"y":3.73},{"time":1.3333,"x":0,"y":0}]},"bone35":{"rotate":[{"time":0,"angle":0,"curve":[0.25,0,0.75,1]},{"time":0.1667,"angle":23.07,"curve":"stepped"},{"time":0.6,"angle":23.07},{"time":0.7667,"angle":37.25,"curve":"stepped"},{"time":0.9,"angle":37.25},{"time":1.3333,"angle":0}],"scale":[{"time":0.6,"x":1,"y":1,"curve":[0.343,0.37,0.679,0.71]},{"time":0.7667,"x":0.769,"y":1,"curve":"stepped"},{"time":0.9,"x":0.769,"y":1,"curve":[0.379,0.6,0.724,1]},{"time":1.3333,"x":1,"y":1}]},"bone36":{"rotate":[{"time":0,"angle":0,"curve":[0.25,0,0.75,1]},{"time":0.1667,"angle":-10.34,"curve":"stepped"},{"time":0.6,"angle":-10.34},{"time":0.7667,"angle":-34.32,"curve":"stepped"},{"time":0.9,"angle":-34.32},{"time":1.3333,"angle":0}],"translate":[{"time":0,"x":0,"y":0,"curve":[0.25,0,0.75,1]},{"time":0.1667,"x":-1.35,"y":0.48,"curve":"stepped"},{"time":0.9,"x":-1.35,"y":0.48},{"time":1.3333,"x":0,"y":0}],"scale":[{"time":0.6,"x":1,"y":1,"curve":[0.242,0,0.667,0.67]},{"time":0.7667,"x":1.214,"y":1,"curve":"stepped"},{"time":0.9,"x":1.214,"y":1,"curve":[0.379,0.6,0.724,1]},{"time":1.3333,"x":1,"y":1}]},"bone37":{"rotate":[{"time":0,"angle":0,"curve":[0.25,0,0.75,1]},{"time":0.1667,"angle":-15.24,"curve":"stepped"},{"time":0.6,"angle":-15.24},{"time":0.7667,"angle":-36.79,"curve":"stepped"},{"time":0.9,"angle":-36.79},{"time":1.3333,"angle":0}],"translate":[{"time":0.6,"x":0,"y":0},{"time":0.7667,"x":3.08,"y":0,"curve":"stepped"},{"time":0.9,"x":3.08,"y":0},{"time":1.3333,"x":0,"y":0}]},"bone38":{"rotate":[{"time":0,"angle":0,"curve":[0.25,0,0.75,1]},{"time":0.1667,"angle":29.12,"curve":"stepped"},{"time":0.6,"angle":29.12},{"time":0.7667,"angle":57.51,"curve":"stepped"},{"time":0.9,"angle":57.51},{"time":1.3333,"angle":0}],"translate":[{"time":0.6,"x":0,"y":0},{"time":0.7667,"x":-1.11,"y":-2.03,"curve":"stepped"},{"time":0.9,"x":-1.11,"y":-2.03},{"time":1.3333,"x":0,"y":0}]},"bone39":{"rotate":[{"time":0.6,"angle":0},{"time":0.7667,"angle":-2.72,"curve":"stepped"},{"time":0.9,"angle":-2.72},{"time":1.3333,"angle":0}]},"bone40":{"rotate":[{"time":0.6,"angle":0},{"time":0.7667,"angle":-15.75,"curve":"stepped"},{"time":0.9,"angle":-15.75},{"time":1.3333,"angle":0}]},"bone58":{"rotate":[{"time":0.7,"angle":0},{"time":0.7667,"angle":-38.43},{"time":0.8333,"angle":-5.75},{"time":0.9,"angle":0}]},"bone59":{"rotate":[{"time":0,"angle":0,"curve":[0.246,0,0.633,0.54]},{"time":0.4667,"angle":-8.62,"curve":[0.356,0.41,0.702,0.79]},{"time":0.8,"angle":-6.89,"curve":[0.367,0.63,0.705,1]},{"time":0.9,"angle":0}]},"bone60":{"rotate":[{"time":0,"angle":0,"curve":[0.246,0,0.633,0.54]},{"time":0.4667,"angle":11.26,"curve":[0.352,0.4,0.696,0.77]},{"time":0.8,"angle":-13.95,"curve":[0.372,0.62,0.711,1]},{"time":0.9,"angle":0}]},"bone61":{"rotate":[{"time":0,"angle":0,"curve":[0.246,0,0.633,0.54]},{"time":0.4667,"angle":-4.08,"curve":[0.343,0.37,0.681,0.71]},{"time":0.7333,"angle":-4.43,"curve":[0.345,0.38,0.68,0.72]},{"time":0.8,"angle":-9.53,"curve":[0.372,0.62,0.711,1]},{"time":0.9,"angle":0}]},"bone62":{"rotate":[{"time":0,"angle":0,"curve":[0.246,0,0.633,0.54]},{"time":0.4667,"angle":11.05,"curve":[0.38,0.53,0.745,1]},{"time":0.9,"angle":0}]},"bone64":{"translate":[{"time":0.6,"x":0,"y":0,"curve":[0.352,0.41,0.689,0.76]},{"time":0.7667,"x":4.09,"y":0,"curve":"stepped"},{"time":0.9,"x":4.09,"y":0,"curve":[0.367,0.63,0.705,1]},{"time":1.3333,"x":0,"y":0}]},"bone66":{"rotate":[{"time":0.2,"angle":0},{"time":0.2667,"angle":-38.47},{"time":0.3333,"angle":0},{"time":0.4,"angle":-38.47},{"time":0.4667,"angle":0},{"time":0.5,"angle":-38.47},{"time":0.5667,"angle":0}]}}},"Dodge":{"slots":{"body1":{"color":[{"time":0.4,"color":"ffffffff"},{"time":0.4667,"color":"ffffff00","curve":"stepped"},{"time":0.8333,"color":"ffffff00"},{"time":0.8667,"color":"ffffffff"}]},"body1 copy":{"color":[{"time":0.3667,"color":"ffffff00"},{"time":0.4333,"color":"ffffffff","curve":"stepped"},{"time":0.8667,"color":"ffffffff"},{"time":0.9,"color":"ffffff00"}],"attachment":[{"time":0,"name":null},{"time":0.3667,"name":"body1 copy"},{"time":1.3333,"name":null}]},"tay1":{"attachment":[{"time":0.3667,"name":null},{"time":0.9,"name":"tay1"}]},"tay1b":{"attachment":[{"time":0.3667,"name":null},{"time":0.9,"name":"tay1b"}]},"tay333":{"attachment":[{"time":0,"name":null},{"time":0.3667,"name":"tay333"},{"time":0.9,"name":null}]},"weapon":{"attachment":[{"time":0.3333,"name":null},{"time":0.9333,"name":"weapon"}]},"weapon2":{"attachment":[{"time":0,"name":null},{"time":0.3333,"name":"weapon"},{"time":0.9333,"name":null}]},"weapon3":{"attachment":[{"time":0,"name":null},{"time":0.3333,"name":"weapon"},{"time":0.9333,"name":null}]}},"bones":{"bone46":{"rotate":[{"time":0,"angle":0},{"time":0.1333,"angle":-16.97},{"time":0.3333,"angle":-94.37},{"time":0.4333,"angle":-84.93,"curve":"stepped"},{"time":0.8333,"angle":-84.93},{"time":0.9333,"angle":-24.6},{"time":1.1333,"angle":0}],"translate":[{"time":0,"x":0,"y":0},{"time":0.0667,"x":14.06,"y":-6.24},{"time":0.1333,"x":18.52,"y":-9.87},{"time":0.2,"x":18.52,"y":-20.59},{"time":0.3333,"x":13.11,"y":-15.35},{"time":0.4333,"x":11.8,"y":-13.82,"curve":"stepped"},{"time":0.8333,"x":11.8,"y":-13.82},{"time":0.9333,"x":15.37,"y":-8.54},{"time":1.1333,"x":0,"y":0}]},"bone57":{"rotate":[{"time":0,"angle":0},{"time":0.3333,"angle":-175.25},{"time":0.3667,"angle":133.45},{"time":0.4333,"angle":129.35,"curve":"stepped"},{"time":0.8333,"angle":129.35},{"time":0.8667,"angle":143.24},{"time":0.9,"angle":-175.25},{"time":0.9333,"angle":103.48},{"time":1.3333,"angle":0}],"translate":[{"time":0,"x":0,"y":0},{"time":0.3333,"x":-29.18,"y":-3.99},{"time":0.3667,"x":-12.53,"y":10.32},{"time":0.4333,"x":-13.86,"y":12.91,"curve":"stepped"},{"time":0.8333,"x":-13.86,"y":12.91},{"time":0.8667,"x":-13.99,"y":8.55},{"time":0.9,"x":-29.18,"y":-3.99},{"time":0.9333,"x":-11.09,"y":10.33},{"time":1.3333,"x":0,"y":0}]},"bone2":{"rotate":[{"time":0.4333,"angle":0,"curve":[0.33,0.32,0.663,0.66]},{"time":0.5,"angle":3.35,"curve":[0.331,0.33,0.665,0.66]},{"time":0.5667,"angle":0,"curve":[0.331,0.33,0.666,0.67]},{"time":0.6333,"angle":3.35,"curve":[0.331,0.33,0.665,0.66]},{"time":0.7,"angle":0,"curve":[0.336,0.34,0.671,0.68]},{"time":0.7667,"angle":3.35,"curve":[0.331,0.33,0.665,0.66]},{"time":0.8333,"angle":0,"curve":"stepped"},{"time":0.9333,"angle":0,"curve":[0.329,0.32,0.665,0.66]},{"time":1.1333,"angle":1.51,"curve":[0.336,0.34,0.671,0.68]},{"time":1.3333,"angle":0}]},"bone5":{"rotate":[{"time":0.3333,"angle":0},{"time":0.4,"angle":10.51,"curve":"stepped"},{"time":0.8333,"angle":10.51},{"time":0.9333,"angle":0}]},"bone6":{"rotate":[{"time":0.9333,"angle":0,"curve":[0.329,0.32,0.665,0.66]},{"time":1.1333,"angle":1.03,"curve":[0.336,0.34,0.671,0.68]},{"time":1.3333,"angle":0}]},"bone7":{"rotate":[{"time":0.4333,"angle":0,"curve":[0.33,0.32,0.663,0.66]},{"time":0.5,"angle":-3,"curve":[0.33,0.32,0.663,0.66]},{"time":0.5667,"angle":0,"curve":[0.331,0.33,0.666,0.67]},{"time":0.6333,"angle":-3,"curve":[0.33,0.32,0.663,0.66]},{"time":0.7,"angle":0,"curve":[0.336,0.34,0.671,0.68]},{"time":0.7667,"angle":-3,"curve":[0.33,0.32,0.663,0.66]},{"time":0.8333,"angle":0}]},"bone9":{"rotate":[{"time":0.9333,"angle":0,"curve":[0.329,0.32,0.665,0.66]},{"time":1.1333,"angle":-3.17,"curve":[0.336,0.34,0.671,0.68]},{"time":1.3333,"angle":0}]},"bone10":{"translate":[{"time":0.3333,"x":0,"y":0},{"time":0.4333,"x":-0.4,"y":1.81,"curve":"stepped"},{"time":0.8333,"x":-0.4,"y":1.81},{"time":0.9333,"x":-0.32,"y":1.45},{"time":1.3333,"x":0,"y":0}]},"bone11":{"rotate":[{"time":0,"angle":0},{"time":0.2,"angle":-13.54},{"time":0.3333,"angle":-0.18},{"time":0.4333,"angle":-0.16,"curve":"stepped"},{"time":0.8333,"angle":-0.16},{"time":0.9333,"angle":-0.13},{"time":1.3333,"angle":0}],"translate":[{"time":0.4333,"x":0,"y":0},{"time":0.5,"x":0.01,"y":-0.74},{"time":0.5667,"x":0,"y":0},{"time":0.6333,"x":0.01,"y":-0.74},{"time":0.7,"x":0,"y":0},{"time":0.7667,"x":0.01,"y":-0.74},{"time":0.8333,"x":0,"y":0}]},"bone13":{"rotate":[{"time":0.3333,"angle":0},{"time":0.4333,"angle":8.02,"curve":"stepped"},{"time":0.8333,"angle":8.02},{"time":0.9333,"angle":0}],"translate":[{"time":0.3333,"x":0,"y":0},{"time":0.4333,"x":-8.08,"y":-1.91,"curve":"stepped"},{"time":0.8333,"x":-8.08,"y":-1.91},{"time":0.8667,"x":-8.44,"y":-1.65},{"time":0.9333,"x":0,"y":0}]},"bone30":{"rotate":[{"time":0,"angle":0,"curve":[0.294,0,0.631,0.37]},{"time":0.2,"angle":15.1,"curve":[0.317,0.27,0.652,0.61]},{"time":0.3333,"angle":0,"curve":[0.325,0.31,0.66,0.64]},{"time":0.4333,"angle":-4.74,"curve":"stepped"},{"time":0.8333,"angle":-4.74,"curve":[0.323,0.3,0.664,0.66]},{"time":0.9333,"angle":-1.18,"curve":[0.336,0.34,0.67,0.68]},{"time":0.9667,"angle":0}]},"bone53":{"rotate":[{"time":0.3333,"angle":0},{"time":0.3667,"angle":-7.13},{"time":0.4333,"angle":-6.64,"curve":"stepped"},{"time":0.8333,"angle":-6.64},{"time":0.9,"angle":0}],"translate":[{"time":0.3333,"x":0,"y":0},{"time":0.3667,"x":5.21,"y":-6.5},{"time":0.4333,"x":4.85,"y":-6.05,"curve":"stepped"},{"time":0.8333,"x":4.85,"y":-6.05},{"time":0.8667,"x":2.88,"y":-4.76},{"time":0.9,"x":0,"y":0}]},"bone38":{"rotate":[{"time":0.3333,"angle":0,"curve":[0.328,0.31,0.662,0.65]},{"time":0.4,"angle":26.17,"curve":"stepped"},{"time":0.8333,"angle":26.17,"curve":[0.331,0.33,0.665,0.66]},{"time":0.9333,"angle":0,"curve":[0.329,0.32,0.665,0.66]},{"time":1.1333,"angle":2.03,"curve":[0.336,0.34,0.671,0.68]},{"time":1.3333,"angle":0}]},"bone29":{"rotate":[{"time":0,"angle":0,"curve":[0.294,0,0.631,0.37]},{"time":0.2,"angle":21.87,"curve":[0.317,0.27,0.652,0.61]},{"time":0.3333,"angle":0,"curve":[0.325,0.31,0.66,0.64]},{"time":0.4333,"angle":-62.53,"curve":[0.327,0.31,0.662,0.65]},{"time":0.5,"angle":-58.91,"curve":[0.335,0.34,0.669,0.67]},{"time":0.5667,"angle":-62.53,"curve":[0.331,0.33,0.666,0.67]},{"time":0.6333,"angle":-58.91,"curve":[0.335,0.34,0.669,0.67]},{"time":0.7,"angle":-62.53,"curve":[0.334,0.34,0.668,0.67]},{"time":0.7667,"angle":-58.91,"curve":[0.335,0.34,0.669,0.67]},{"time":0.8333,"angle":-62.53,"curve":[0.323,0.3,0.664,0.66]},{"time":0.9333,"angle":-15.64,"curve":[0.336,0.34,0.67,0.68]},{"time":0.9667,"angle":0}],"translate":[{"time":0.3333,"x":0,"y":0},{"time":0.4333,"x":-0.75,"y":-0.84,"curve":"stepped"},{"time":0.8333,"x":-0.75,"y":-0.84},{"time":0.9333,"x":-0.19,"y":-0.21},{"time":0.9667,"x":0,"y":0}]},"bone37":{"rotate":[{"time":0.3333,"angle":0,"curve":[0.328,0.31,0.662,0.65]},{"time":0.4,"angle":-12.69,"curve":"stepped"},{"time":0.8333,"angle":-12.69,"curve":[0.331,0.33,0.665,0.66]},{"time":0.9333,"angle":0,"curve":[0.329,0.32,0.665,0.66]},{"time":1.1333,"angle":-1.13,"curve":[0.336,0.34,0.671,0.68]},{"time":1.3333,"angle":0}]},"bone39":{"rotate":[{"time":0.3333,"angle":0,"curve":[0.328,0.31,0.662,0.65]},{"time":0.4,"angle":-12.14,"curve":"stepped"},{"time":0.8333,"angle":-12.14,"curve":[0.331,0.33,0.665,0.66]},{"time":0.9333,"angle":0,"curve":[0.329,0.32,0.665,0.66]},{"time":1.1333,"angle":-2.04,"curve":[0.336,0.34,0.671,0.68]},{"time":1.3333,"angle":0}]},"bone40":{"rotate":[{"time":0.3333,"angle":0,"curve":[0.328,0.31,0.662,0.65]},{"time":0.4,"angle":-7,"curve":"stepped"},{"time":0.8333,"angle":-7,"curve":[0.331,0.33,0.665,0.66]},{"time":0.9333,"angle":0}]},"bone60":{"rotate":[{"time":0.4333,"angle":0,"curve":[0.33,0.31,0.663,0.65]},{"time":0.5,"angle":10.03,"curve":[0.33,0.32,0.664,0.65]},{"time":0.5667,"angle":0,"curve":[0.328,0.3,0.661,0.64]},{"time":0.6333,"angle":10.03,"curve":[0.33,0.32,0.664,0.65]},{"time":0.7,"angle":0,"curve":[0.328,0.31,0.662,0.64]},{"time":0.7667,"angle":10.03,"curve":[0.33,0.32,0.664,0.65]},{"time":0.8333,"angle":0}]},"bone43":{"rotate":[{"time":0,"angle":0,"curve":[0.294,0,0.631,0.37]},{"time":0.2,"angle":-49.12,"curve":[0.317,0.27,0.652,0.61]},{"time":0.3333,"angle":12.26,"curve":[0.325,0.31,0.66,0.64]},{"time":0.4333,"angle":-22,"curve":"stepped"},{"time":0.8333,"angle":-22,"curve":[0.329,0.32,0.663,0.65]},{"time":0.9,"angle":12.26,"curve":[0.325,0.31,0.66,0.64]},{"time":0.9333,"angle":-17.76,"curve":[0.33,0.32,0.671,0.68]},{"time":1.1333,"angle":0}],"translate":[{"time":0,"x":0,"y":0,"curve":[0.294,0,0.631,0.37]},{"time":0.2,"x":1.89,"y":0.49,"curve":[0.317,0.27,0.652,0.61]},{"time":0.3333,"x":1.69,"y":0.44,"curve":[0.325,0.31,0.66,0.64]},{"time":0.4333,"x":1.51,"y":0.39,"curve":"stepped"},{"time":0.8333,"x":1.51,"y":0.39,"curve":[0.329,0.32,0.663,0.65]},{"time":0.9,"x":1.69,"y":0.44,"curve":[0.325,0.31,0.66,0.64]},{"time":0.9333,"x":1.22,"y":0.32,"curve":[0.33,0.32,0.671,0.68]},{"time":1.3333,"x":0,"y":0}]},"bone44":{"rotate":[{"time":0,"angle":0,"curve":[0.294,0,0.631,0.37]},{"time":0.2,"angle":-7.09,"curve":[0.312,0.25,0.649,0.6]},{"time":0.3333,"angle":8.4,"curve":[0.33,0.32,0.664,0.66]},{"time":0.3667,"angle":-50.49,"curve":[0.33,0.32,0.664,0.66]},{"time":0.4333,"angle":-46.44,"curve":"stepped"},{"time":0.8333,"angle":-46.44,"curve":[0.331,0.32,0.664,0.66]},{"time":0.9,"angle":8.4,"curve":[0.33,0.32,0.664,0.66]},{"time":0.9333,"angle":-37.25,"curve":[0.334,0.33,0.674,0.69]},{"time":1.1333,"angle":0}]},"bone54":{"rotate":[{"time":0.3333,"angle":0},{"time":0.3667,"angle":44.88},{"time":0.4333,"angle":41.79},{"time":0.5,"angle":36.73},{"time":0.5667,"angle":41.79},{"time":0.6333,"angle":36.73},{"time":0.7,"angle":41.79},{"time":0.7667,"angle":36.73},{"time":0.8333,"angle":41.79},{"time":0.9,"angle":0}]},"bone36":{"rotate":[{"time":0.3333,"angle":0,"curve":[0.328,0.31,0.662,0.65]},{"time":0.4,"angle":9.99,"curve":"stepped"},{"time":0.8333,"angle":9.99,"curve":[0.331,0.33,0.665,0.66]},{"time":0.9333,"angle":0}]},"bone58":{"rotate":[{"time":0.9333,"angle":0},{"time":1.1333,"angle":1.64},{"time":1.3333,"angle":0}]},"bone59":{"rotate":[{"time":0.4333,"angle":0,"curve":[0.33,0.31,0.664,0.65]},{"time":0.5,"angle":-2.25,"curve":[0.33,0.31,0.664,0.65]},{"time":0.5667,"angle":0,"curve":[0.328,0.3,0.661,0.64]},{"time":0.6333,"angle":-2.25,"curve":[0.33,0.31,0.664,0.65]},{"time":0.7,"angle":0,"curve":[0.328,0.31,0.662,0.64]},{"time":0.7667,"angle":-2.25,"curve":[0.33,0.31,0.664,0.65]},{"time":0.8333,"angle":0,"curve":"stepped"},{"time":0.9333,"angle":0,"curve":[0.326,0.29,0.66,0.63]},{"time":1.1333,"angle":1.92,"curve":[0.327,0.3,0.661,0.64]},{"time":1.3333,"angle":0}]},"bone31":{"translate":[{"time":0.3333,"x":0,"y":0,"curve":[0.325,0.31,0.66,0.64]},{"time":0.4333,"x":-0.87,"y":-2.68,"curve":"stepped"},{"time":0.8333,"x":-0.87,"y":-2.68,"curve":[0.323,0.3,0.664,0.66]},{"time":0.9333,"x":-0.22,"y":-0.67,"curve":[0.336,0.34,0.67,0.68]},{"time":0.9667,"x":0,"y":0}]},"bone34":{"rotate":[{"time":0.3333,"angle":0,"curve":[0.328,0.31,0.662,0.65]},{"time":0.4,"angle":17.02,"curve":"stepped"},{"time":0.8333,"angle":17.02,"curve":[0.331,0.33,0.665,0.66]},{"time":0.9333,"angle":0,"curve":[0.329,0.32,0.665,0.66]},{"time":1.1333,"angle":1.28,"curve":[0.336,0.34,0.671,0.68]},{"time":1.3333,"angle":0}]},"bone45":{"rotate":[{"time":0,"angle":0,"curve":[0.305,0,0.64,0.36]},{"time":0.1333,"angle":-48.59,"curve":[0.323,0.27,0.657,0.61]},{"time":0.2,"angle":-28.65,"curve":[0.317,0.27,0.652,0.61]},{"time":0.3333,"angle":-58.73,"curve":[0.325,0.31,0.66,0.64]},{"time":0.4333,"angle":-52.48,"curve":"stepped"},{"time":0.8333,"angle":-52.48,"curve":[0.329,0.32,0.663,0.65]},{"time":0.9,"angle":-58.73,"curve":[0.325,0.31,0.66,0.64]},{"time":0.9333,"angle":-42.37,"curve":[0.33,0.32,0.671,0.68]},{"time":1.3333,"angle":0}]},"bone35":{"rotate":[{"time":0.3333,"angle":0,"curve":[0.328,0.31,0.662,0.65]},{"time":0.4,"angle":-27.17,"curve":"stepped"},{"time":0.8333,"angle":-27.17,"curve":[0.331,0.33,0.665,0.66]},{"time":0.9333,"angle":0,"curve":[0.329,0.32,0.665,0.66]},{"time":1.1333,"angle":-2.25,"curve":[0.336,0.34,0.671,0.68]},{"time":1.3333,"angle":0}]},"bone32":{"rotate":[{"time":0.3333,"angle":0},{"time":0.4333,"angle":-37.64,"curve":"stepped"},{"time":0.8333,"angle":-37.64},{"time":0.9333,"angle":-30.11},{"time":1.3333,"angle":0}]},"bone61":{"rotate":[{"time":0.9333,"angle":0,"curve":[0.325,0.3,0.659,0.64]},{"time":1.1333,"angle":-6.99,"curve":[0.328,0.32,0.662,0.65]},{"time":1.3333,"angle":0}]},"bone66":{"rotate":[{"time":0,"angle":0},{"time":0.2,"angle":-2.47},{"time":0.3333,"angle":-2.18},{"time":0.4333,"angle":-1.97,"curve":"stepped"},{"time":0.8333,"angle":-1.97},{"time":0.9,"angle":-2.18},{"time":0.9333,"angle":-1.57},{"time":1.3333,"angle":0}]},"bone8":{"rotate":[{"time":0.3333,"angle":0,"curve":[0.328,0.31,0.662,0.65]},{"time":0.4,"angle":-13.71,"curve":"stepped"},{"time":0.8333,"angle":-13.71,"curve":[0.331,0.33,0.665,0.66]},{"time":0.9333,"angle":0}]},"bone":{"translate":[{"time":0.3333,"x":0,"y":0},{"time":0.4,"x":0,"y":-6.63,"curve":"stepped"},{"time":0.8333,"x":0,"y":-6.63},{"time":0.9333,"x":0,"y":0},{"time":1.1333,"x":0,"y":-0.33},{"time":1.3333,"x":0,"y":0}]}},"drawOrder":[{"time":0.3333,"offsets":[{"slot":"weapon3","offset":13},{"slot":"weapon2","offset":4}]}]},"Hit":{"slots":{"body1 copy":{"attachment":[{"time":0,"name":null}]},"tay333":{"attachment":[{"time":0,"name":null}]},"weapon2":{"attachment":[{"time":0,"name":null}]},"weapon3":{"attachment":[{"time":0,"name":null}]}},"bones":{"bone2":{"rotate":[{"time":0,"angle":0},{"time":0.1667,"angle":-23.42},{"time":0.6667,"angle":0}],"translate":[{"time":0,"x":0,"y":0},{"time":0.1667,"x":5.79,"y":3.35},{"time":0.6667,"x":0,"y":0}]},"bone3":{"rotate":[{"time":0,"angle":0},{"time":0.1667,"angle":-20.23},{"time":0.6667,"angle":0}]},"bone5":{"rotate":[{"time":0,"angle":0},{"time":0.1667,"angle":-10.56},{"time":0.6667,"angle":0}],"translate":[{"time":0,"x":0,"y":0},{"time":0.1667,"x":7.88,"y":2.31},{"time":0.6667,"x":0,"y":0}]},"bone6":{"rotate":[{"time":0,"angle":0,"curve":[0.299,0,0.636,0.36]},{"time":0.1667,"angle":-0.92,"curve":[0.298,0.2,0.756,1]},{"time":0.6667,"angle":0}]},"bone7":{"rotate":[{"time":0,"angle":0,"curve":[0.299,0,0.636,0.36]},{"time":0.1667,"angle":-6.05,"curve":[0.298,0.2,0.756,1]},{"time":0.6667,"angle":0}]},"bone8":{"rotate":[{"time":0,"angle":0,"curve":[0.266,0,0.618,0.42]},{"time":0.1667,"angle":-28.38,"curve":[0.349,0.39,0.757,1]},{"time":0.6667,"angle":0}],"translate":[{"time":0,"x":0,"y":0,"curve":[0.299,0,0.636,0.36]},{"time":0.1667,"x":5.79,"y":3.35,"curve":[0.298,0.2,0.756,1]},{"time":0.6667,"x":0,"y":0}]},"bone9":{"rotate":[{"time":0,"angle":0,"curve":[0.266,0,0.618,0.42]},{"time":0.1667,"angle":-19.13,"curve":[0.349,0.39,0.757,1]},{"time":0.6667,"angle":0}]},"bone10":{"rotate":[{"time":0,"angle":0},{"time":0.1667,"angle":-8.48},{"time":0.6667,"angle":0}],"translate":[{"time":0,"x":0,"y":0},{"time":0.1667,"x":8.18,"y":3.35},{"time":0.6667,"x":0,"y":0}]},"bone11":{"rotate":[{"time":0,"angle":0},{"time":0.1667,"angle":-14.99},{"time":0.6667,"angle":4.02},{"time":1.3333,"angle":0}]},"bone12":{"rotate":[{"time":0,"angle":0},{"time":0.1667,"angle":-7.01},{"time":0.6667,"angle":4.86},{"time":1.3333,"angle":0}]},"bone13":{"rotate":[{"time":0,"angle":0},{"time":0.1667,"angle":-18.24},{"time":0.6667,"angle":0}]},"bone29":{"rotate":[{"time":0,"angle":0,"curve":[0.299,0,0.636,0.36]},{"time":0.1667,"angle":-31.92,"curve":[0.298,0.2,0.756,1]},{"time":0.6667,"angle":0}]},"bone31":{"rotate":[{"time":0,"angle":0,"curve":[0.266,0,0.618,0.42]},{"time":0.1667,"angle":59.06,"curve":[0.349,0.39,0.757,1]},{"time":0.6667,"angle":0}]},"bone33":{"rotate":[{"time":0,"angle":0,"curve":[0.266,0,0.618,0.42]},{"time":0.1667,"angle":-30.43,"curve":[0.349,0.39,0.757,1]},{"time":0.6667,"angle":0}]},"bone43":{"rotate":[{"time":0,"angle":0,"curve":[0.299,0,0.636,0.36]},{"time":0.1667,"angle":-22.45,"curve":[0.298,0.2,0.756,1]},{"time":0.6667,"angle":-4.69,"curve":[0.299,0,0.636,0.36]},{"time":1.3333,"angle":0}]},"bone44":{"rotate":[{"time":0,"angle":0,"curve":[0.266,0,0.618,0.42]},{"time":0.1667,"angle":-5.35,"curve":[0.349,0.39,0.757,1]},{"time":0.6667,"angle":0}]},"bone45":{"rotate":[{"time":0,"angle":0,"curve":[0.299,0,0.636,0.36]},{"time":0.1667,"angle":-11.88,"curve":[0.298,0.2,0.756,1]},{"time":0.6667,"angle":0}]},"bone34":{"rotate":[{"time":0,"angle":0,"curve":[0.299,0,0.636,0.36]},{"time":0.1667,"angle":-9.04,"curve":[0.298,0.2,0.756,1]},{"time":0.6667,"angle":0.99,"curve":[0.299,0,0.636,0.36]},{"time":1.3333,"angle":0}],"translate":[{"time":0,"x":0,"y":0,"curve":[0.299,0,0.636,0.36]},{"time":0.1667,"x":9.77,"y":0.36,"curve":[0.298,0.2,0.756,1]},{"time":0.6667,"x":0,"y":0}]},"bone35":{"rotate":[{"time":0,"angle":0,"curve":[0.299,0,0.636,0.36]},{"time":0.1667,"angle":3.7,"curve":[0.298,0.2,0.756,1]},{"time":0.6667,"angle":-1.11,"curve":[0.299,0,0.636,0.36]},{"time":1.3333,"angle":0}]},"bone37":{"rotate":[{"time":0,"angle":0,"curve":[0.299,0,0.636,0.36]},{"time":0.1667,"angle":-13.31,"curve":[0.298,0.2,0.756,1]},{"time":0.6667,"angle":0}],"translate":[{"time":0,"x":0,"y":0,"curve":[0.299,0,0.636,0.36]},{"time":0.1667,"x":8.62,"y":-1.77,"curve":[0.298,0.2,0.756,1]},{"time":0.6667,"x":0,"y":0}]},"bone38":{"rotate":[{"time":0,"angle":0,"curve":[0.299,0,0.636,0.36]},{"time":0.1667,"angle":11.28,"curve":[0.298,0.2,0.756,1]},{"time":0.6667,"angle":0}]},"bone39":{"rotate":[{"time":0,"angle":0,"curve":[0.299,0,0.636,0.36]},{"time":0.1667,"angle":12.88,"curve":[0.298,0.2,0.756,1]},{"time":0.6667,"angle":0}]},"bone56":{"rotate":[{"time":0,"angle":0},{"time":0.1667,"angle":-38.28},{"time":0.6667,"angle":0}],"translate":[{"time":0,"x":0,"y":0},{"time":0.1667,"x":5.8,"y":3.35},{"time":0.6667,"x":0,"y":0}]},"bone58":{"rotate":[{"time":0,"angle":0},{"time":0.1667,"angle":-13.91},{"time":0.6667,"angle":6.63},{"time":1.3333,"angle":0}]},"bone59":{"rotate":[{"time":0,"angle":0,"curve":[0.266,0,0.618,0.42]},{"time":0.1667,"angle":-3.32,"curve":[0.349,0.39,0.757,1]},{"time":0.6667,"angle":0}]},"bone60":{"rotate":[{"time":0,"angle":0,"curve":[0.266,0,0.618,0.42]},{"time":0.1667,"angle":-15.55,"curve":[0.349,0.39,0.757,1]},{"time":0.6667,"angle":0}]},"bone61":{"rotate":[{"time":0,"angle":0,"curve":[0.266,0,0.618,0.42]},{"time":0.1667,"angle":-8.05,"curve":[0.349,0.39,0.757,1]},{"time":0.6667,"angle":0}]},"bone62":{"rotate":[{"time":0,"angle":0,"curve":[0.276,0,0.621,0.4]},{"time":0.1667,"angle":-22.65,"curve":[0.333,0.33,0.758,1]},{"time":0.6667,"angle":0}]}}},"Idle":{"slots":{"body1 copy":{"attachment":[{"time":0,"name":null}]},"tay333":{"attachment":[{"time":0,"name":null}]},"weapon2":{"attachment":[{"time":0,"name":null}]},"weapon3":{"attachment":[{"time":0,"name":null}]}},"bones":{"bone":{"translate":[{"time":0,"x":0,"y":0},{"time":0.6667,"x":0,"y":-2.36},{"time":1.3333,"x":0,"y":0}]},"bone2":{"rotate":[{"time":0,"angle":0,"curve":[0.25,0,0.75,1]},{"time":0.4,"angle":-4.15,"curve":[0.25,0,0.75,1]},{"time":0.9,"angle":0.94,"curve":[0.25,0,0.75,1]},{"time":1.3333,"angle":0}]},"bone3":{"rotate":[{"time":0,"angle":0},{"time":0.4333,"angle":-6.47},{"time":0.9667,"angle":1.68},{"time":1.3333,"angle":0}]},"bone4":{"rotate":[{"time":0,"angle":0,"curve":[0.25,0,0.75,1]},{"time":0.4667,"angle":2.06,"curve":[0.25,0,0.75,1]},{"time":1.0333,"angle":10.24,"curve":[0.25,0,0.75,1]},{"time":1.3333,"angle":0}]},"bone5":{"rotate":[{"time":0,"angle":0},{"time":0.6667,"angle":6.2},{"time":1.3333,"angle":0}]},"bone6":{"rotate":[{"time":0,"angle":0,"curve":[0.25,0,0.75,1]},{"time":0.6667,"angle":11.05,"curve":[0.25,0,0.75,1]},{"time":1.3333,"angle":0}]},"bone7":{"rotate":[{"time":0,"angle":0,"curve":[0.25,0,0.75,1]},{"time":0.6667,"angle":-8.77,"curve":[0.25,0,0.75,1]},{"time":1.3333,"angle":0}]},"bone8":{"rotate":[{"time":0,"angle":0,"curve":[0.25,0,0.75,1]},{"time":0.6667,"angle":-8.45,"curve":[0.25,0,0.75,1]},{"time":1.3333,"angle":0}]},"bone9":{"rotate":[{"time":0,"angle":0,"curve":[0.25,0,0.75,1]},{"time":0.6667,"angle":-8.28,"curve":[0.25,0,0.75,1]},{"time":1.3333,"angle":0}]},"bone29":{"rotate":[{"time":0,"angle":0,"curve":[0.25,0,0.75,1]},{"time":0.6667,"angle":3.73,"curve":[0.25,0,0.75,1]},{"time":1.3333,"angle":0}]},"bone30":{"rotate":[{"time":0,"angle":0,"curve":[0.25,0,0.75,1]},{"time":0.6667,"angle":1.16,"curve":[0.25,0,0.75,1]},{"time":1.3333,"angle":0}]},"bone31":{"rotate":[{"time":0,"angle":0,"curve":[0.25,0,0.75,1]},{"time":0.6667,"angle":-4.83,"curve":[0.25,0,0.75,1]},{"time":1.3333,"angle":0}]},"bone33":{"rotate":[{"time":0,"angle":0,"curve":[0.25,0,0.75,1]},{"time":0.6667,"angle":9.63,"curve":[0.25,0,0.75,1]},{"time":1.3333,"angle":0}]},"bone43":{"rotate":[{"time":0,"angle":0,"curve":[0.25,0,0.75,1]},{"time":0.6667,"angle":-1.43,"curve":[0.25,0,0.75,1]},{"time":1.3333,"angle":0}]},"bone44":{"rotate":[{"time":0,"angle":0,"curve":[0.25,0,0.75,1]},{"time":0.6667,"angle":-1.24,"curve":[0.25,0,0.75,1]},{"time":1.3333,"angle":0}]},"bone45":{"rotate":[{"time":0,"angle":0,"curve":[0.25,0,0.75,1]},{"time":0.6667,"angle":-3.18,"curve":[0.25,0,0.75,1]},{"time":1.3333,"angle":0}]},"bone34":{"rotate":[{"time":0,"angle":0,"curve":[0.25,0,0.75,1]},{"time":0.6667,"angle":5.44,"curve":[0.25,0,0.75,1]},{"time":1.3333,"angle":0}]},"bone35":{"rotate":[{"time":0,"angle":0,"curve":[0.25,0,0.75,1]},{"time":0.6667,"angle":-9.25,"curve":[0.25,0,0.75,1]},{"time":1.3333,"angle":0}]},"bone36":{"rotate":[{"time":0,"angle":0,"curve":[0.25,0,0.75,1]},{"time":0.6667,"angle":5.32,"curve":[0.25,0,0.75,1]},{"time":1.3333,"angle":0}]},"bone37":{"rotate":[{"time":0,"angle":0,"curve":[0.25,0,0.75,1]},{"time":0.6667,"angle":-4.89,"curve":[0.25,0,0.75,1]},{"time":1.3333,"angle":0}]},"bone38":{"rotate":[{"time":0,"angle":0,"curve":[0.25,0,0.75,1]},{"time":0.6667,"angle":10.81,"curve":[0.25,0,0.75,1]},{"time":1.3333,"angle":0}]},"bone39":{"rotate":[{"time":0,"angle":0,"curve":[0.25,0,0.75,1]},{"time":0.6667,"angle":-19.59,"curve":[0.25,0,0.75,1]},{"time":1.3333,"angle":0}]},"bone40":{"rotate":[{"time":0,"angle":0,"curve":[0.25,0,0.75,1]},{"time":0.6667,"angle":17.83,"curve":[0.25,0,0.75,1]},{"time":1.3333,"angle":0}]},"bone58":{"rotate":[{"time":0,"angle":0},{"time":0.3333,"angle":-3.21},{"time":0.8333,"angle":1.08},{"time":1.3333,"angle":0}]},"bone59":{"rotate":[{"time":0,"angle":0,"curve":[0.272,0,0.619,0.41]},{"time":0.3667,"angle":-5.08,"curve":[0.316,0.28,0.671,0.68]},{"time":0.8667,"angle":2.36,"curve":[0.382,0.57,0.737,1]},{"time":1.3333,"angle":0}]},"bone60":{"rotate":[{"time":0,"angle":0,"curve":[0.269,0,0.618,0.42]},{"time":0.4,"angle":-4.55,"curve":[0.321,0.29,0.675,0.69]},{"time":0.9,"angle":3.41,"curve":[0.382,0.57,0.734,1]},{"time":1.3333,"angle":0}]},"bone61":{"rotate":[{"time":0,"angle":0,"curve":[0.244,0,0.646,0.59]},{"time":0.4333,"angle":-17.51,"curve":[0.354,0.41,0.693,0.76]},{"time":0.9333,"angle":3.15,"curve":[0.369,0.63,0.707,1]},{"time":1.3333,"angle":0}]},"bone62":{"rotate":[{"time":0,"angle":0,"curve":[0.243,0,0.655,0.63]},{"time":0.4667,"angle":-0.33,"curve":[0.356,0.42,0.694,0.78]},{"time":0.9667,"angle":12.54,"curve":[0.365,0.64,0.701,1]},{"time":1.3333,"angle":0}]}}},"In":{"slots":{"body1 copy":{"attachment":[{"time":0,"name":null}]},"tay333":{"attachment":[{"time":0,"name":null}]},"weapon2":{"attachment":[{"time":0,"name":null}]},"weapon3":{"attachment":[{"time":0,"name":null}]}},"bones":{"bone":{"translate":[{"time":0,"x":380.93,"y":45.86},{"time":0.5,"x":-6.37,"y":-1.77},{"time":0.6667,"x":0,"y":-2.36},{"time":1.3333,"x":0,"y":0}]},"bone2":{"rotate":[{"time":0,"angle":0,"curve":[0.25,0,0.75,1]},{"time":0.4,"angle":-4.15,"curve":[0.284,0,0.625,0.38]},{"time":0.5,"angle":20.71,"curve":[0.304,0.24,0.655,0.63]},{"time":0.6667,"angle":-16.19,"curve":[0.378,0.52,0.748,1]},{"time":0.8333,"angle":-7.26,"curve":[0.284,0.14,0.633,0.53]},{"time":1,"angle":6.17,"curve":[0.36,0.43,0.755,1]},{"time":1.3333,"angle":0}]},"bone3":{"rotate":[{"time":0,"angle":0},{"time":0.4333,"angle":-6.47},{"time":0.6667,"angle":-2.9},{"time":0.9667,"angle":1.68},{"time":1.3333,"angle":0}]},"bone4":{"rotate":[{"time":0,"angle":0,"curve":[0.25,0,0.75,1]},{"time":0.4667,"angle":2.06,"curve":[0.262,0,0.618,0.44]},{"time":0.6667,"angle":4.58,"curve":[0.355,0.41,0.756,1]},{"time":1.0333,"angle":10.24,"curve":[0.25,0,0.75,1]},{"time":1.3333,"angle":0}]},"bone5":{"rotate":[{"time":0,"angle":0},{"time":0.5,"angle":29.56},{"time":0.6667,"angle":-10.6},{"time":0.9333,"angle":7.37},{"time":1.3333,"angle":0}]},"bone6":{"rotate":[{"time":0,"angle":0,"curve":[0.25,0,0.75,1]},{"time":0.6667,"angle":11.05,"curve":[0.25,0,0.75,1]},{"time":1.3333,"angle":0}]},"bone7":{"rotate":[{"time":0,"angle":0,"curve":[0.25,0,0.75,1]},{"time":0.6667,"angle":-8.77,"curve":[0.25,0,0.75,1]},{"time":1.3333,"angle":0}]},"bone8":{"rotate":[{"time":0,"angle":0,"curve":[0.25,0,0.75,1]},{"time":0.6667,"angle":-8.45,"curve":[0.25,0,0.75,1]},{"time":1.3333,"angle":0}]},"bone9":{"rotate":[{"time":0,"angle":0,"curve":[0.25,0,0.75,1]},{"time":0.6667,"angle":-8.28,"curve":[0.25,0,0.75,1]},{"time":1.3333,"angle":0}]},"bone10":{"rotate":[{"time":0,"angle":0},{"time":0.5,"angle":-7.83},{"time":0.6667,"angle":7.73},{"time":1,"angle":-1.65},{"time":1.3333,"angle":0}]},"bone29":{"rotate":[{"time":0,"angle":0,"curve":[0.25,0,0.625,0.5]},{"time":0.3333,"angle":18.42,"curve":[0.375,0.5,0.75,1]},{"time":0.6667,"angle":-21.4,"curve":[0.25,0,0.75,1]},{"time":1.3333,"angle":0}]},"bone30":{"rotate":[{"time":0,"angle":0,"curve":[0.25,0,0.75,1]},{"time":0.6667,"angle":1.16,"curve":[0.25,0,0.75,1]},{"time":1.3333,"angle":0}]},"bone31":{"rotate":[{"time":0,"angle":0,"curve":[0.25,0,0.75,1]},{"time":0.6667,"angle":-4.83,"curve":[0.25,0,0.75,1]},{"time":1.3333,"angle":0}]},"bone33":{"rotate":[{"time":0,"angle":0,"curve":[0.25,0,0.75,1]},{"time":0.6667,"angle":9.63,"curve":[0.25,0,0.75,1]},{"time":1.3333,"angle":0}]},"bone43":{"rotate":[{"time":0,"angle":0,"curve":[0.25,0,0.625,0.5]},{"time":0.3333,"angle":-71.7,"curve":[0.343,0.36,0.686,0.73]},{"time":0.6667,"angle":-82.62,"curve":[0.25,0,0.75,1]},{"time":1.3333,"angle":0}]},"bone44":{"rotate":[{"time":0,"angle":0,"curve":[0.25,0,0.75,1]},{"time":0.6667,"angle":-1.24,"curve":[0.25,0,0.75,1]},{"time":1.3333,"angle":0}]},"bone45":{"rotate":[{"time":0,"angle":0,"curve":[0.25,0,0.75,1]},{"time":0.6667,"angle":-3.18,"curve":[0.25,0,0.75,1]},{"time":1.3333,"angle":0}]},"bone34":{"rotate":[{"time":0,"angle":0,"curve":[0.25,0,0.75,1]},{"time":0.6667,"angle":5.44,"curve":[0.25,0,0.75,1]},{"time":1.3333,"angle":0}]},"bone35":{"rotate":[{"time":0,"angle":0,"curve":[0.242,0,0.667,0.67]},{"time":0.5,"angle":-18.57,"curve":[0.379,0.6,0.724,1]},{"time":0.6667,"angle":-9.25,"curve":[0.25,0,0.75,1]},{"time":1.3333,"angle":0}]},"bone36":{"rotate":[{"time":0,"angle":0,"curve":[0.25,0,0.75,1]},{"time":0.6667,"angle":5.32,"curve":[0.25,0,0.75,1]},{"time":1.3333,"angle":0}]},"bone37":{"rotate":[{"time":0,"angle":0,"curve":[0.25,0,0.625,0.5]},{"time":0.3333,"angle":22.34,"curve":[0.347,0.38,0.694,0.76]},{"time":0.5,"angle":-11.24,"curve":[0.375,0.62,0.716,1]},{"time":0.6667,"angle":-4.89,"curve":[0.25,0,0.75,1]},{"time":1.3333,"angle":0}],"translate":[{"time":0,"x":0,"y":0,"curve":[0.276,0,0.621,0.4]},{"time":0.3333,"x":-6.14,"y":0.82,"curve":[0.314,0.27,0.657,0.64]},{"time":0.6667,"x":0,"y":0}]},"bone38":{"rotate":[{"time":0,"angle":0,"curve":[0.25,0,0.625,0.5]},{"time":0.3333,"angle":28.07,"curve":[0.343,0.36,0.686,0.73]},{"time":0.5,"angle":38.55,"curve":[0.379,0.6,0.724,1]},{"time":0.6667,"angle":10.81,"curve":[0.25,0,0.75,1]},{"time":1.3333,"angle":0}]},"bone39":{"rotate":[{"time":0,"angle":0,"curve":[0.25,0,0.75,1]},{"time":0.6667,"angle":-19.59,"curve":[0.25,0,0.75,1]},{"time":1.3333,"angle":0}]},"bone40":{"rotate":[{"time":0,"angle":0,"curve":[0.25,0,0.75,1]},{"time":0.6667,"angle":17.83,"curve":[0.25,0,0.75,1]},{"time":1.3333,"angle":0}]},"bone56":{"rotate":[{"time":0,"angle":0},{"time":0.3333,"angle":26.05},{"time":0.5,"angle":-4.67},{"time":0.6667,"angle":0},{"time":0.8333,"angle":5.91},{"time":1.1333,"angle":-2.79},{"time":1.3333,"angle":0}]},"bone58":{"rotate":[{"time":0,"angle":0},{"time":0.3333,"angle":22.83},{"time":0.5,"angle":-6.45},{"time":0.6667,"angle":-0.35},{"time":0.8333,"angle":6.99},{"time":1.1333,"angle":-2.36},{"time":1.3333,"angle":0}]},"bone59":{"rotate":[{"time":0,"angle":0,"curve":[0.276,0,0.621,0.4]},{"time":0.3333,"angle":21.67,"curve":[0.33,0.32,0.664,0.66]},{"time":0.3667,"angle":-5.08,"curve":[0.324,0.3,0.659,0.64]},{"time":0.5,"angle":-20.89,"curve":[0.329,0.32,0.664,0.66]},{"time":0.6667,"angle":-0.66,"curve":[0.336,0.34,0.671,0.68]},{"time":0.8333,"angle":7.79,"curve":[0.335,0.34,0.668,0.67]},{"time":0.8667,"angle":2.36,"curve":[0.354,0.41,0.694,0.77]},{"time":1.1333,"angle":-4.54,"curve":[0.369,0.63,0.706,1]},{"time":1.3333,"angle":0}]},"bone60":{"rotate":[{"time":0,"angle":0,"curve":[0.276,0,0.621,0.4]},{"time":0.3333,"angle":22.61,"curve":[0.328,0.31,0.662,0.65]},{"time":0.4,"angle":-4.55,"curve":[0.327,0.31,0.661,0.65]},{"time":0.5,"angle":-20.72,"curve":[0.329,0.32,0.664,0.66]},{"time":0.6667,"angle":-0.32,"curve":[0.336,0.34,0.671,0.68]},{"time":0.8333,"angle":8.29,"curve":[0.337,0.34,0.67,0.68]},{"time":0.9,"angle":3.41,"curve":[0.353,0.41,0.692,0.76]},{"time":1.1333,"angle":-4.17,"curve":[0.369,0.63,0.706,1]},{"time":1.3333,"angle":0}]},"bone61":{"rotate":[{"time":0,"angle":0,"curve":[0.25,0,0.625,0.5]},{"time":0.3333,"angle":13.43,"curve":[0.337,0.34,0.673,0.69]},{"time":0.4333,"angle":-17.51,"curve":[0.335,0.34,0.669,0.67]},{"time":0.5,"angle":-32.06,"curve":[0.339,0.35,0.673,0.69]},{"time":0.6667,"angle":-6.93,"curve":[0.342,0.37,0.676,0.7]},{"time":0.8333,"angle":5.62,"curve":[0.34,0.36,0.673,0.7]},{"time":0.9333,"angle":3.15,"curve":[0.349,0.43,0.684,0.77]},{"time":1.1333,"angle":-4.22,"curve":[0.355,0.65,0.69,1]},{"time":1.3333,"angle":0}]},"bone62":{"rotate":[{"time":0,"angle":0,"curve":[0.25,0,0.625,0.5]},{"time":0.3333,"angle":25.83,"curve":[0.339,0.35,0.679,0.7]},{"time":0.4667,"angle":-0.33,"curve":[0.334,0.34,0.668,0.67]},{"time":0.5,"angle":-17.01,"curve":[0.34,0.36,0.674,0.69]},{"time":0.6667,"angle":5.48,"curve":[0.342,0.37,0.676,0.7]},{"time":0.8333,"angle":15.62,"curve":[0.342,0.37,0.675,0.71]},{"time":0.9667,"angle":12.54,"curve":[0.346,0.42,0.68,0.76]},{"time":1.1333,"angle":-0.9,"curve":[0.353,0.65,0.687,1]},{"time":1.3333,"angle":0}]},"bone63":{"translate":[{"time":0,"x":372.25,"y":0,"curve":[0.29,0,0.629,0.38]},{"time":0.1667,"x":259.46,"y":-0.43,"curve":[0.311,0.25,0.649,0.6]},{"time":0.3333,"x":128.79,"y":-1.27,"curve":[0.325,0.31,0.663,0.65]},{"time":0.5,"x":-2.9,"y":-2.25,"curve":[0.375,0.5,0.75,1]},{"time":0.6667,"x":0,"y":0}],"scale":[{"time":0,"x":0.664,"y":0.664,"curve":[0.25,0,0.625,0.5]},{"time":0.5,"x":1,"y":1}]},"bone64":{"translate":[{"time":0,"x":372.25,"y":0,"curve":[0.29,0,0.629,0.38]},{"time":0.1667,"x":259.46,"y":-0.43,"curve":[0.311,0.25,0.649,0.6]},{"time":0.3333,"x":128.79,"y":-1.27,"curve":[0.325,0.31,0.663,0.65]},{"time":0.5,"x":-2.9,"y":-2.25,"curve":[0.375,0.5,0.75,1]},{"time":0.6667,"x":0,"y":0}],"scale":[{"time":0,"x":0.664,"y":0.664,"curve":[0.25,0,0.625,0.5]},{"time":0.5,"x":1,"y":1}]},"bone65":{"translate":[{"time":0,"x":372.25,"y":0,"curve":[0.29,0,0.629,0.38]},{"time":0.1667,"x":259.46,"y":-0.43,"curve":[0.311,0.25,0.649,0.6]},{"time":0.3333,"x":128.79,"y":-1.27,"curve":[0.325,0.31,0.663,0.65]},{"time":0.5,"x":-2.9,"y":-2.25,"curve":[0.375,0.5,0.75,1]},{"time":0.6667,"x":0,"y":0}],"scale":[{"time":0,"x":0.664,"y":0.664,"curve":[0.25,0,0.625,0.5]},{"time":0.5,"x":1,"y":1}]}}},"Out":{"slots":{"body1 copy":{"attachment":[{"time":0,"name":null}]},"shadow":{"color":[{"time":0.1667,"color":"ffffffff"},{"time":0.3667,"color":"ffffff00"}]},"tay333":{"attachment":[{"time":0,"name":null}]},"weapon2":{"attachment":[{"time":0,"name":null}]},"weapon3":{"attachment":[{"time":0,"name":null}]}},"bones":{"bone":{"translate":[{"time":0,"x":0,"y":0},{"time":0.1667,"x":0,"y":-4.52},{"time":0.2,"x":34.51,"y":19.13},{"time":0.3333,"x":172.55,"y":75.54},{"time":0.5333,"x":379.62,"y":118.69},{"time":0.7333,"x":379.62,"y":40.7},{"time":1,"x":420.36,"y":116.36}],"scale":[{"time":0,"x":1,"y":1},{"time":0.1667,"x":1,"y":0.944},{"time":0.5333,"x":1,"y":1}]},"bone2":{"rotate":[{"time":0,"angle":0},{"time":0.1667,"angle":4.41},{"time":0.2333,"angle":-45.93},{"time":0.3333,"angle":-18.73},{"time":0.7333,"angle":0}],"translate":[{"time":0,"x":0,"y":0},{"time":0.2333,"x":5.79,"y":3.35},{"time":0.3333,"x":4.64,"y":2.68},{"time":0.7333,"x":0,"y":0}]},"bone3":{"rotate":[{"time":0,"angle":0},{"time":0.2333,"angle":-20.23},{"time":0.3333,"angle":-16.18},{"time":0.7333,"angle":0}]},"bone5":{"rotate":[{"time":0,"angle":0},{"time":0.1667,"angle":0.31},{"time":0.2333,"angle":-25.39},{"time":0.3333,"angle":-8.45},{"time":0.7333,"angle":0}],"translate":[{"time":0,"x":0,"y":0},{"time":0.2333,"x":7.88,"y":2.31},{"time":0.3333,"x":6.3,"y":1.85},{"time":0.7333,"x":0,"y":0}]},"bone6":{"rotate":[{"time":0,"angle":0,"curve":[0.299,0,0.636,0.36]},{"time":0.2333,"angle":-0.92,"curve":[0.306,0.22,0.644,0.58]},{"time":0.3333,"angle":-0.75,"curve":[0.345,0.38,0.757,1]},{"time":0.7333,"angle":0}]},"bone7":{"rotate":[{"time":0,"angle":0,"curve":[0.299,0,0.636,0.36]},{"time":0.2333,"angle":-6.05,"curve":[0.306,0.22,0.644,0.58]},{"time":0.3333,"angle":-4.92,"curve":[0.345,0.38,0.757,1]},{"time":0.7333,"angle":0}]},"bone8":{"rotate":[{"time":0,"angle":0,"curve":[0.314,0,0.648,0.35]},{"time":0.2333,"angle":-50.91,"curve":[0.287,0.13,0.632,0.52]},{"time":0.3333,"angle":-43.98,"curve":[0.37,0.48,0.752,1]},{"time":0.7333,"angle":-40.8,"curve":[0.25,0,0.75,1]},{"time":1,"angle":0}],"translate":[{"time":0,"x":0,"y":0,"curve":[0.299,0,0.636,0.36]},{"time":0.2333,"x":5.79,"y":3.35,"curve":[0.306,0.22,0.644,0.58]},{"time":0.3333,"x":4.71,"y":2.73,"curve":[0.345,0.38,0.757,1]},{"time":0.7333,"x":0,"y":0}]},"bone9":{"rotate":[{"time":0,"angle":0,"curve":[0.266,0,0.618,0.42]},{"time":0.2333,"angle":-19.13,"curve":[0.325,0.31,0.661,0.65]},{"time":0.3333,"angle":-14.6,"curve":[0.37,0.48,0.752,1]},{"time":0.7333,"angle":0}]},"bone10":{"rotate":[{"time":0,"angle":0},{"time":0.1667,"angle":-5.09},{"time":0.2333,"angle":47.8},{"time":0.3333,"angle":29.16},{"time":0.7333,"angle":0}],"translate":[{"time":0,"x":0,"y":0},{"time":0.2333,"x":8.18,"y":3.35},{"time":0.3333,"x":6.55,"y":2.68},{"time":0.7333,"x":0,"y":0}]},"bone11":{"rotate":[{"time":0,"angle":0},{"time":0.2333,"angle":-14.99},{"time":0.3333,"angle":-11.19},{"time":0.7333,"angle":4.02},{"time":1,"angle":0}]},"bone12":{"rotate":[{"time":0,"angle":0},{"time":0.2333,"angle":-7.01},{"time":0.3333,"angle":-4.64},{"time":0.7333,"angle":4.86},{"time":1,"angle":0}]},"bone13":{"rotate":[{"time":0,"angle":0},{"time":0.2333,"angle":-18.24},{"time":0.3333,"angle":-14.59},{"time":0.7333,"angle":0}]},"bone29":{"rotate":[{"time":0,"angle":0,"curve":[0.299,0,0.636,0.36]},{"time":0.2333,"angle":-31.92,"curve":[0.306,0.22,0.644,0.58]},{"time":0.3333,"angle":-25.96,"curve":[0.345,0.38,0.757,1]},{"time":0.7333,"angle":0}]},"bone31":{"rotate":[{"time":0,"angle":0,"curve":[0.266,0,0.618,0.42]},{"time":0.2333,"angle":59.06,"curve":[0.325,0.31,0.661,0.65]},{"time":0.3333,"angle":45.09,"curve":[0.37,0.48,0.752,1]},{"time":0.7333,"angle":0}]},"bone33":{"rotate":[{"time":0,"angle":0,"curve":[0.266,0,0.618,0.42]},{"time":0.2333,"angle":-30.43,"curve":[0.325,0.31,0.661,0.65]},{"time":0.3333,"angle":-23.23,"curve":[0.37,0.48,0.752,1]},{"time":0.7333,"angle":0}]},"bone43":{"rotate":[{"time":0,"angle":0,"curve":[0.305,0,0.64,0.36]},{"time":0.3333,"angle":-105.91,"curve":[0.345,0.38,0.757,1]},{"time":0.7333,"angle":-164.59,"curve":[0.299,0,0.636,0.36]},{"time":1,"angle":-129.52}]},"bone44":{"rotate":[{"time":0,"angle":0,"curve":[0.285,0,0.626,0.38]},{"time":0.3333,"angle":41.09,"curve":[0.37,0.48,0.752,1]},{"time":0.7333,"angle":44.32,"curve":[0.25,0,0.75,1]},{"time":1,"angle":0}]},"bone45":{"rotate":[{"time":0,"angle":0,"curve":[0.299,0,0.636,0.36]},{"time":0.3333,"angle":-9.66,"curve":[0.345,0.38,0.757,1]},{"time":0.7333,"angle":-22.15,"curve":[0.299,0,0.636,0.36]},{"time":1,"angle":0}]},"bone34":{"rotate":[{"time":0,"angle":0,"curve":[0.311,0,0.646,0.35]},{"time":0.1667,"angle":-4.33,"curve":[0.322,0.26,0.656,0.59]},{"time":0.2333,"angle":-55.17,"curve":[0.313,0.25,0.649,0.59]},{"time":0.3333,"angle":-63.39,"curve":[0.327,0.31,0.661,0.65]},{"time":0.7333,"angle":0.99,"curve":[0.299,0,0.636,0.36]},{"time":1,"angle":0}],"translate":[{"time":0,"x":0,"y":0,"curve":[0.311,0,0.646,0.35]},{"time":0.1667,"x":2.94,"y":0.15,"curve":[0.322,0.26,0.656,0.59]},{"time":0.2333,"x":-2.3,"y":0.36,"curve":[0.306,0.22,0.644,0.58]},{"time":0.3333,"x":7.95,"y":0.29,"curve":[0.345,0.38,0.757,1]},{"time":0.7333,"x":0,"y":0}]},"bone35":{"rotate":[{"time":0,"angle":0,"curve":[0.299,0,0.636,0.36]},{"time":0.2333,"angle":3.7,"curve":[0.306,0.22,0.644,0.58]},{"time":0.3333,"angle":2.8,"curve":[0.345,0.38,0.757,1]},{"time":0.7333,"angle":-1.11,"curve":[0.299,0,0.636,0.36]},{"time":1,"angle":0}]},"bone37":{"rotate":[{"time":0,"angle":0,"curve":[0.311,0,0.646,0.35]},{"time":0.1667,"angle":-4.76,"curve":[0.322,0.26,0.656,0.59]},{"time":0.2333,"angle":-68.8,"curve":[0.306,0.22,0.644,0.58]},{"time":0.3333,"angle":-56.47,"curve":[0.345,0.38,0.757,1]},{"time":0.7333,"angle":0}],"translate":[{"time":0,"x":0,"y":0,"curve":[0.299,0,0.636,0.36]},{"time":0.2333,"x":8.62,"y":-1.77,"curve":[0.306,0.22,0.644,0.58]},{"time":0.3333,"x":7.01,"y":-1.44,"curve":[0.345,0.38,0.757,1]},{"time":0.7333,"x":0,"y":0}]},"bone38":{"rotate":[{"time":0,"angle":0,"curve":[0.299,0,0.636,0.36]},{"time":0.2333,"angle":11.28,"curve":[0.306,0.22,0.644,0.58]},{"time":0.3333,"angle":9.17,"curve":[0.345,0.38,0.757,1]},{"time":0.7333,"angle":0}]},"bone39":{"rotate":[{"time":0,"angle":0,"curve":[0.299,0,0.636,0.36]},{"time":0.2333,"angle":12.88,"curve":[0.306,0.22,0.644,0.58]},{"time":0.3333,"angle":10.48,"curve":[0.345,0.38,0.757,1]},{"time":0.7333,"angle":0}]},"bone56":{"rotate":[{"time":0,"angle":0},{"time":0.2333,"angle":-38.28},{"time":0.3333,"angle":-30.62},{"time":0.7333,"angle":0}],"translate":[{"time":0,"x":0,"y":0},{"time":0.2333,"x":5.8,"y":3.35},{"time":0.3333,"x":4.64,"y":2.68},{"time":0.7333,"x":0,"y":0}]},"bone58":{"rotate":[{"time":0,"angle":0},{"time":0.2333,"angle":-13.91},{"time":0.3333,"angle":-9.8},{"time":0.7333,"angle":6.63},{"time":1,"angle":0}]},"bone59":{"rotate":[{"time":0,"angle":0,"curve":[0.266,0,0.618,0.42]},{"time":0.2333,"angle":-3.32,"curve":[0.325,0.31,0.661,0.65]},{"time":0.3333,"angle":-2.54,"curve":[0.37,0.48,0.752,1]},{"time":0.7333,"angle":0}]},"bone60":{"rotate":[{"time":0,"angle":0,"curve":[0.266,0,0.618,0.42]},{"time":0.2333,"angle":-15.55,"curve":[0.325,0.31,0.661,0.65]},{"time":0.3333,"angle":-11.87,"curve":[0.37,0.48,0.752,1]},{"time":0.7333,"angle":0}]},"bone61":{"rotate":[{"time":0,"angle":0,"curve":[0.266,0,0.618,0.42]},{"time":0.2333,"angle":-8.05,"curve":[0.325,0.31,0.661,0.65]},{"time":0.3333,"angle":-6.14,"curve":[0.37,0.48,0.752,1]},{"time":0.7333,"angle":0}]},"bone62":{"rotate":[{"time":0,"angle":0,"curve":[0.276,0,0.621,0.4]},{"time":0.2333,"angle":-22.65,"curve":[0.319,0.29,0.656,0.63]},{"time":0.3333,"angle":-17.62,"curve":[0.363,0.44,0.755,1]},{"time":0.7333,"angle":0}]},"bone63":{"translate":[{"time":0.1667,"x":0,"y":0,"curve":[0.325,0.29,0.658,0.63]},{"time":0.2,"x":1.83,"y":0,"curve":[0.311,0.26,0.651,0.61]},{"time":0.3333,"x":141.64,"y":0,"curve":[0.363,0.44,0.755,1]},{"time":0.7333,"x":374.4,"y":0,"curve":[0.25,0,0.75,1]},{"time":1,"x":373.23,"y":0}]},"bone64":{"translate":[{"time":0.1667,"x":0,"y":0,"curve":[0.325,0.29,0.658,0.63]},{"time":0.2,"x":13.25,"y":0,"curve":[0.311,0.26,0.651,0.61]},{"time":0.3333,"x":141.64,"y":0,"curve":[0.363,0.44,0.755,1]},{"time":0.7333,"x":374.4,"y":0,"curve":[0.25,0,0.75,1]},{"time":1,"x":373.23,"y":0}]},"bone65":{"translate":[{"time":0.1667,"x":0,"y":0,"curve":[0.301,0.22,0.645,0.59]},{"time":0.3333,"x":141.64,"y":0,"curve":[0.363,0.44,0.755,1]},{"time":0.7333,"x":374.4,"y":0,"curve":[0.25,0,0.75,1]},{"time":1,"x":373.23,"y":0}]}},"deform":{"default":{"shadow":{"shadow":[{"time":1,"vertices":[-43.77841,119.44788,-43.77841,119.44788,-81.43667,97.7359,-43.77841,119.44788,-81.43667,97.7359,-85.70889,94.01147,-85.70889,94.01147,-85.70889,94.01147,-85.70889,94.01147,-43.77841,119.44788,-81.43667,97.7359,-85.70889,94.01147,-43.77841,119.44788,-81.43667,97.7359]}]}}}}}}