{"skeleton":{"hash":"5WbGkv0+uNdECr7FLLIsu2KNTHE","spine":"3.8.75","x":-95.74,"y":-90.96,"width":187,"height":174,"images":"./images/","audio":"C:/Users/LINH/Downloads/Telegram Desktop/New folder/minipoker"},"bones":[{"name":"root"},{"name":"Layer 2","parent":"root","x":-9.55,"y":0.36},{"name":"MINI POKER","parent":"root","x":-4,"y":-56.68},{"name":"MINI POKER2","parent":"MINI POKER"}],"slots":[{"name":"Group 45 copy 2","bone":"root","attachment":"Group 45 copy 2"},{"name":"Layer 2","bone":"Layer 2","attachment":"Layer 2"},{"name":"MINI POKER","bone":"MINI POKER","attachment":"MINI POKER"},{"name":"MINI POKER2","bone":"MINI POKER2","attachment":"MINI POKER","blend":"additive"}],"skins":[{"name":"default","attachments":{"Layer 2":{"Layer 2":{"x":7.31,"y":-2.32,"width":187,"height":150}},"Group 45 copy 2":{"Group 45 copy 2":{"x":-5.74,"y":-3.96,"width":170,"height":174}},"MINI POKER":{"MINI POKER":{"x":-0.73,"y":0.1,"width":158,"height":28}},"MINI POKER2":{"MINI POKER":{"x":-0.73,"y":0.1,"width":158,"height":28}}}}],"animations":{"animation":{"slots":{"MINI POKER2":{"color":[{"color":"ffffff00"},{"time":0.2,"color":"ffffff12"},{"time":0.4,"color":"ffffffff"},{"time":0.5333,"color":"ffffff12"},{"time":0.6667,"color":"ffffffff"},{"time":0.8,"color":"ffffff12"},{"time":2.0667,"color":"ffffff00"},{"time":2.2667,"color":"ffffff12"},{"time":2.4667,"color":"ffffffff"},{"time":2.6,"color":"ffffff12"},{"time":2.7333,"color":"ffffffff"},{"time":2.8667,"color":"ffffff12"},{"time":4.3,"color":"ffffff00"},{"time":4.5,"color":"ffffff12"},{"time":4.7,"color":"ffffffff"},{"time":4.8333,"color":"ffffff12"},{"time":4.9667,"color":"ffffffff"},{"time":5.1,"color":"ffffff12"},{"time":6.1667,"color":"ffffff00"},{"time":6.3667,"color":"ffffff12"},{"time":6.5667,"color":"ffffffff"},{"time":6.7,"color":"ffffff12"},{"time":6.8333,"color":"ffffffff"},{"time":6.9667,"color":"ffffff12"}]}},"bones":{"Layer 2":{"rotate":[{"curve":0.25,"c3":0.75},{"time":0.4,"angle":8.63,"curve":0.25,"c3":0.75},{"time":0.8,"angle":-10.03,"curve":0.25,"c3":0.75},{"time":1.2,"angle":-14.42,"curve":0.25,"c3":0.75},{"time":1.5333,"curve":0.25,"c3":0.75},{"time":1.9333,"angle":8.63,"curve":0.25,"c3":0.75},{"time":2.3333,"angle":-10.03,"curve":0.25,"c3":0.75},{"time":2.7333,"angle":-14.42,"curve":0.25,"c3":0.75},{"time":3.0667,"curve":0.25,"c3":0.75},{"time":3.4667,"angle":8.63,"curve":0.25,"c3":0.75},{"time":3.8667,"angle":-10.03,"curve":0.25,"c3":0.75},{"time":4.2667,"angle":-14.42,"curve":0.25,"c3":0.75},{"time":4.6,"curve":0.25,"c3":0.75},{"time":5,"angle":8.63,"curve":0.25,"c3":0.75},{"time":5.4,"angle":-10.03,"curve":0.25,"c3":0.75},{"time":5.8,"angle":-14.42,"curve":0.25,"c3":0.75},{"time":6.1333,"curve":0.25,"c3":0.75},{"time":6.5333,"angle":8.63,"curve":0.25,"c3":0.75},{"time":6.9333,"angle":-10.03,"curve":0.25,"c3":0.75},{"time":7.3333,"angle":-14.42,"curve":0.25,"c3":0.75},{"time":7.6667}],"translate":[{"curve":0.376,"c3":0.381},{"time":0.8,"y":25.08,"curve":0.529,"c3":0.372},{"time":1.5333,"curve":0.376,"c3":0.381},{"time":2.3333,"y":25.08,"curve":0.529,"c3":0.372},{"time":3.0667,"curve":0.376,"c3":0.381},{"time":3.8667,"y":25.08,"curve":0.529,"c3":0.372},{"time":4.6,"curve":0.376,"c3":0.381},{"time":5.4,"y":25.08,"curve":0.529,"c3":0.372},{"time":6.1333,"curve":0.376,"c3":0.381},{"time":6.9333,"y":25.08,"curve":0.529,"c3":0.372},{"time":7.6667}]},"MINI POKER":{"scale":[{},{"time":0.8333,"x":1.068,"y":1.068,"curve":0.25,"c3":0.75},{"time":0.9667,"x":1.006,"y":1.006,"curve":0.25,"c3":0.75},{"time":1.0667,"x":1.078,"y":1.078,"curve":0.25,"c3":0.75},{"time":1.1667,"x":0.981,"y":0.981,"curve":0.25,"c3":0.75},{"time":1.2667,"x":1.078,"y":1.078,"curve":0.25,"c3":0.75},{"time":1.3667},{"time":2.9,"x":1.068,"y":1.068,"curve":0.25,"c3":0.75},{"time":3.0333,"x":1.006,"y":1.006,"curve":0.25,"c3":0.75},{"time":3.1333,"x":1.078,"y":1.078,"curve":0.25,"c3":0.75},{"time":3.2333,"x":0.981,"y":0.981,"curve":0.25,"c3":0.75},{"time":3.3333,"x":1.078,"y":1.078,"curve":0.25,"c3":0.75},{"time":3.4333},{"time":5.0333,"x":1.068,"y":1.068,"curve":0.25,"c3":0.75},{"time":5.1667,"x":1.006,"y":1.006,"curve":0.25,"c3":0.75},{"time":5.2667,"x":1.078,"y":1.078,"curve":0.25,"c3":0.75},{"time":5.3667,"x":0.981,"y":0.981,"curve":0.25,"c3":0.75},{"time":5.4667,"x":1.078,"y":1.078,"curve":0.25,"c3":0.75},{"time":5.5667},{"time":7.1667,"x":1.068,"y":1.068,"curve":0.25,"c3":0.75},{"time":7.3,"x":1.006,"y":1.006,"curve":0.25,"c3":0.75},{"time":7.4,"x":1.078,"y":1.078,"curve":0.25,"c3":0.75},{"time":7.5,"x":0.981,"y":0.981,"curve":0.25,"c3":0.75},{"time":7.6,"x":1.078,"y":1.078,"curve":0.25,"c3":0.75},{"time":7.7}]}}}}}